{"licenses":[{"name":"","id":0,"url":""}],"info":{"contributor":"","date_created":"","description":"","url":"","version":"","year":""},"categories":[{"id":1,"name":"Falling","supercategory":"","keypoints":["1","2","3","4","5","6","7","8","9","10","11","12","13","14","15","16","17"],"skeleton":[[6,12],[3,1],[4,6],[14,16],[17,15],[9,11],[6,8],[7,13],[4,2],[1,2],[7,9],[6,7],[13,15],[3,2],[3,5],[12,14],[8,10],[13,12],[7,5]]},{"id":19,"name":"Sitting","supercategory":"","keypoints":["1","2","3","4","5","6","7","8","9","10","11","12","13","14","15","16","17"],"skeleton":[[6,12],[3,1],[4,6],[14,16],[5,7],[9,11],[15,17],[6,8],[7,13],[2,4],[1,2],[7,9],[7,6],[3,2],[3,5],[12,14],[8,10],[13,12],[13,15]]},{"id":37,"name":"Standing","supercategory":"","keypoints":["1","2","3","4","5","6","7","8","9","10","11","12","13","14","15","16","17"],"skeleton":[[6,12],[3,1],[12,13],[14,16],[9,11],[15,17],[6,8],[7,13],[2,4],[2,1],[6,4],[7,9],[13,15],[7,6],[3,2],[3,5],[12,14],[8,10],[7,5]]},{"id":55,"name":"Walking","supercategory":"","keypoints":["1","2","3","4","5","6","7","8","9","10","11","12","13","14","15","16","17"],"skeleton":[[6,12],[3,1],[4,6],[12,13],[14,16],[9,11],[15,17],[6,8],[7,13],[2,4],[1,2],[7,9],[13,15],[7,6],[3,2],[3,5],[12,14],[8,10],[7,5]]},{"id":73,"name":"Bending Down","supercategory":"","keypoints":["1","2","3","4","5","6","7","8","9","10","11","12","13","14","15","16","17"],"skeleton":[[6,12],[3,1],[4,6],[12,13],[14,16],[5,7],[9,11],[15,17],[6,8],[7,13],[2,4],[1,2],[7,9],[6,7],[3,5],[12,14],[8,10],[2,3],[13,15]]},{"id":91,"name":"Wearing/fixing shoes","supercategory":"","keypoints":["1","2","3","4","5","6","7","8","9","10","11","12","13","14","15","16","17"],"skeleton":[[6,12],[3,1],[4,6],[12,13],[14,16],[5,7],[9,11],[15,17],[6,8],[2,4],[1,2],[13,7],[7,9],[7,6],[3,5],[12,14],[8,10],[2,3],[13,15]]},{"id":109,"name":"Waving hands","supercategory":"","keypoints":["1","2","3","4","5","6","7","8","9","10","11","12","13","14","15","16","17"],"skeleton":[[6,12],[3,1],[4,6],[14,16],[5,7],[9,11],[15,17],[6,8],[7,13],[2,4],[1,2],[7,9],[7,6],[3,5],[12,14],[8,10],[2,3],[13,12],[13,15]]},{"id":127,"name":"Sleeping","supercategory":"","keypoints":["1","2","3","4","5","6","7","8","9","10","11","12","13","14","15","16","17"],"skeleton":[[3,1],[4,6],[14,16],[9,11],[15,17],[6,8],[7,13],[12,6],[2,4],[1,2],[7,9],[6,7],[13,15],[3,5],[12,14],[8,10],[2,3],[13,12],[7,5]]}],"images":[{"id":1,"width":640,"height":640,"file_name":"frame_000000.png","license":0,"flickr_url":"","coco_url":"","date_captured":0},{"id":2,"width":640,"height":640,"file_name":"frame_000001.png","license":0,"flickr_url":"","coco_url":"","date_captured":0},{"id":3,"width":640,"height":640,"file_name":"frame_000002.png","license":0,"flickr_url":"","coco_url":"","date_captured":0},{"id":4,"width":640,"height":640,"file_name":"frame_000003.png","license":0,"flickr_url":"","coco_url":"","date_captured":0},{"id":5,"width":640,"height":640,"file_name":"frame_000004.png","license":0,"flickr_url":"","coco_url":"","date_captured":0},{"id":6,"width":640,"height":640,"file_name":"frame_000005.png","license":0,"flickr_url":"","coco_url":"","date_captured":0},{"id":7,"width":640,"height":640,"file_name":"frame_000006.png","license":0,"flickr_url":"","coco_url":"","date_captured":0},{"id":8,"width":640,"height":640,"file_name":"frame_000007.png","license":0,"flickr_url":"","coco_url":"","date_captured":0},{"id":9,"width":640,"height":640,"file_name":"frame_000008.png","license":0,"flickr_url":"","coco_url":"","date_captured":0},{"id":10,"width":640,"height":640,"file_name":"frame_000009.png","license":0,"flickr_url":"","coco_url":"","date_captured":0},{"id":11,"width":640,"height":640,"file_name":"frame_000010.png","license":0,"flickr_url":"","coco_url":"","date_captured":0},{"id":12,"width":640,"height":640,"file_name":"frame_000011.png","license":0,"flickr_url":"","coco_url":"","date_captured":0},{"id":13,"width":640,"height":640,"file_name":"frame_000012.png","license":0,"flickr_url":"","coco_url":"","date_captured":0},{"id":14,"width":640,"height":640,"file_name":"frame_000013.png","license":0,"flickr_url":"","coco_url":"","date_captured":0},{"id":15,"width":640,"height":640,"file_name":"frame_000014.png","license":0,"flickr_url":"","coco_url":"","date_captured":0},{"id":16,"width":640,"height":640,"file_name":"frame_000015.png","license":0,"flickr_url":"","coco_url":"","date_captured":0},{"id":17,"width":640,"height":640,"file_name":"frame_000016.png","license":0,"flickr_url":"","coco_url":"","date_captured":0},{"id":18,"width":640,"height":640,"file_name":"frame_000017.png","license":0,"flickr_url":"","coco_url":"","date_captured":0},{"id":19,"width":640,"height":640,"file_name":"frame_000018.png","license":0,"flickr_url":"","coco_url":"","date_captured":0},{"id":20,"width":640,"height":640,"file_name":"frame_000019.png","license":0,"flickr_url":"","coco_url":"","date_captured":0},{"id":21,"width":640,"height":640,"file_name":"frame_000020.png","license":0,"flickr_url":"","coco_url":"","date_captured":0},{"id":22,"width":640,"height":640,"file_name":"frame_000021.png","license":0,"flickr_url":"","coco_url":"","date_captured":0},{"id":23,"width":640,"height":640,"file_name":"frame_000022.png","license":0,"flickr_url":"","coco_url":"","date_captured":0},{"id":24,"width":640,"height":640,"file_name":"frame_000023.png","license":0,"flickr_url":"","coco_url":"","date_captured":0},{"id":25,"width":640,"height":640,"file_name":"frame_000024.png","license":0,"flickr_url":"","coco_url":"","date_captured":0},{"id":26,"width":640,"height":640,"file_name":"frame_000025.png","license":0,"flickr_url":"","coco_url":"","date_captured":0},{"id":27,"width":640,"height":640,"file_name":"frame_000026.png","license":0,"flickr_url":"","coco_url":"","date_captured":0},{"id":28,"width":640,"height":640,"file_name":"frame_000027.png","license":0,"flickr_url":"","coco_url":"","date_captured":0},{"id":29,"width":640,"height":640,"file_name":"frame_000028.png","license":0,"flickr_url":"","coco_url":"","date_captured":0},{"id":30,"width":640,"height":640,"file_name":"frame_000029.png","license":0,"flickr_url":"","coco_url":"","date_captured":0},{"id":31,"width":640,"height":640,"file_name":"frame_000030.png","license":0,"flickr_url":"","coco_url":"","date_captured":0},{"id":32,"width":640,"height":640,"file_name":"frame_000031.png","license":0,"flickr_url":"","coco_url":"","date_captured":0},{"id":33,"width":640,"height":640,"file_name":"frame_000032.png","license":0,"flickr_url":"","coco_url":"","date_captured":0},{"id":34,"width":640,"height":640,"file_name":"frame_000033.png","license":0,"flickr_url":"","coco_url":"","date_captured":0},{"id":35,"width":640,"height":640,"file_name":"frame_000034.png","license":0,"flickr_url":"","coco_url":"","date_captured":0},{"id":36,"width":640,"height":640,"file_name":"frame_000035.png","license":0,"flickr_url":"","coco_url":"","date_captured":0},{"id":37,"width":640,"height":640,"file_name":"frame_000036.png","license":0,"flickr_url":"","coco_url":"","date_captured":0},{"id":38,"width":640,"height":640,"file_name":"frame_000037.png","license":0,"flickr_url":"","coco_url":"","date_captured":0},{"id":39,"width":640,"height":640,"file_name":"frame_000038.png","license":0,"flickr_url":"","coco_url":"","date_captured":0},{"id":40,"width":640,"height":640,"file_name":"frame_000039.png","license":0,"flickr_url":"","coco_url":"","date_captured":0},{"id":41,"width":640,"height":640,"file_name":"frame_000040.png","license":0,"flickr_url":"","coco_url":"","date_captured":0},{"id":42,"width":640,"height":640,"file_name":"frame_000041.png","license":0,"flickr_url":"","coco_url":"","date_captured":0},{"id":43,"width":640,"height":640,"file_name":"frame_000042.png","license":0,"flickr_url":"","coco_url":"","date_captured":0},{"id":44,"width":640,"height":640,"file_name":"frame_000043.png","license":0,"flickr_url":"","coco_url":"","date_captured":0},{"id":45,"width":640,"height":640,"file_name":"frame_000044.png","license":0,"flickr_url":"","coco_url":"","date_captured":0},{"id":46,"width":640,"height":640,"file_name":"frame_000045.png","license":0,"flickr_url":"","coco_url":"","date_captured":0},{"id":47,"width":640,"height":640,"file_name":"frame_000046.png","license":0,"flickr_url":"","coco_url":"","date_captured":0},{"id":48,"width":640,"height":640,"file_name":"frame_000047.png","license":0,"flickr_url":"","coco_url":"","date_captured":0},{"id":49,"width":640,"height":640,"file_name":"frame_000048.png","license":0,"flickr_url":"","coco_url":"","date_captured":0},{"id":50,"width":640,"height":640,"file_name":"frame_000049.png","license":0,"flickr_url":"","coco_url":"","date_captured":0},{"id":51,"width":640,"height":640,"file_name":"frame_000050.png","license":0,"flickr_url":"","coco_url":"","date_captured":0},{"id":52,"width":640,"height":640,"file_name":"frame_000051.png","license":0,"flickr_url":"","coco_url":"","date_captured":0},{"id":53,"width":640,"height":640,"file_name":"frame_000052.png","license":0,"flickr_url":"","coco_url":"","date_captured":0},{"id":54,"width":640,"height":640,"file_name":"frame_000053.png","license":0,"flickr_url":"","coco_url":"","date_captured":0},{"id":55,"width":640,"height":640,"file_name":"frame_000054.png","license":0,"flickr_url":"","coco_url":"","date_captured":0},{"id":56,"width":640,"height":640,"file_name":"frame_000055.png","license":0,"flickr_url":"","coco_url":"","date_captured":0},{"id":57,"width":640,"height":640,"file_name":"frame_000056.png","license":0,"flickr_url":"","coco_url":"","date_captured":0},{"id":58,"width":640,"height":640,"file_name":"frame_000057.png","license":0,"flickr_url":"","coco_url":"","date_captured":0},{"id":59,"width":640,"height":640,"file_name":"frame_000058.png","license":0,"flickr_url":"","coco_url":"","date_captured":0},{"id":60,"width":640,"height":640,"file_name":"frame_000059.png","license":0,"flickr_url":"","coco_url":"","date_captured":0},{"id":61,"width":640,"height":640,"file_name":"frame_000060.png","license":0,"flickr_url":"","coco_url":"","date_captured":0},{"id":62,"width":640,"height":640,"file_name":"frame_000061.png","license":0,"flickr_url":"","coco_url":"","date_captured":0},{"id":63,"width":640,"height":640,"file_name":"frame_000062.png","license":0,"flickr_url":"","coco_url":"","date_captured":0},{"id":64,"width":640,"height":640,"file_name":"frame_000063.png","license":0,"flickr_url":"","coco_url":"","date_captured":0},{"id":65,"width":640,"height":640,"file_name":"frame_000064.png","license":0,"flickr_url":"","coco_url":"","date_captured":0},{"id":66,"width":640,"height":640,"file_name":"frame_000065.png","license":0,"flickr_url":"","coco_url":"","date_captured":0},{"id":67,"width":640,"height":640,"file_name":"frame_000066.png","license":0,"flickr_url":"","coco_url":"","date_captured":0},{"id":68,"width":640,"height":640,"file_name":"frame_000067.png","license":0,"flickr_url":"","coco_url":"","date_captured":0},{"id":69,"width":640,"height":640,"file_name":"frame_000068.png","license":0,"flickr_url":"","coco_url":"","date_captured":0},{"id":70,"width":640,"height":640,"file_name":"frame_000069.png","license":0,"flickr_url":"","coco_url":"","date_captured":0},{"id":71,"width":640,"height":640,"file_name":"frame_000070.png","license":0,"flickr_url":"","coco_url":"","date_captured":0},{"id":72,"width":640,"height":640,"file_name":"frame_000071.png","license":0,"flickr_url":"","coco_url":"","date_captured":0},{"id":73,"width":640,"height":640,"file_name":"frame_000072.png","license":0,"flickr_url":"","coco_url":"","date_captured":0},{"id":74,"width":640,"height":640,"file_name":"frame_000073.png","license":0,"flickr_url":"","coco_url":"","date_captured":0},{"id":75,"width":640,"height":640,"file_name":"frame_000074.png","license":0,"flickr_url":"","coco_url":"","date_captured":0},{"id":76,"width":640,"height":640,"file_name":"frame_000075.png","license":0,"flickr_url":"","coco_url":"","date_captured":0},{"id":77,"width":640,"height":640,"file_name":"frame_000076.png","license":0,"flickr_url":"","coco_url":"","date_captured":0},{"id":78,"width":640,"height":640,"file_name":"frame_000077.png","license":0,"flickr_url":"","coco_url":"","date_captured":0},{"id":79,"width":640,"height":640,"file_name":"frame_000078.png","license":0,"flickr_url":"","coco_url":"","date_captured":0},{"id":80,"width":640,"height":640,"file_name":"frame_000079.png","license":0,"flickr_url":"","coco_url":"","date_captured":0},{"id":81,"width":640,"height":640,"file_name":"frame_000080.png","license":0,"flickr_url":"","coco_url":"","date_captured":0},{"id":82,"width":640,"height":640,"file_name":"frame_000081.png","license":0,"flickr_url":"","coco_url":"","date_captured":0},{"id":83,"width":640,"height":640,"file_name":"frame_000082.png","license":0,"flickr_url":"","coco_url":"","date_captured":0},{"id":84,"width":640,"height":640,"file_name":"frame_000083.png","license":0,"flickr_url":"","coco_url":"","date_captured":0},{"id":85,"width":640,"height":640,"file_name":"frame_000084.png","license":0,"flickr_url":"","coco_url":"","date_captured":0},{"id":86,"width":640,"height":640,"file_name":"frame_000085.png","license":0,"flickr_url":"","coco_url":"","date_captured":0},{"id":87,"width":640,"height":640,"file_name":"frame_000086.png","license":0,"flickr_url":"","coco_url":"","date_captured":0},{"id":88,"width":640,"height":640,"file_name":"frame_000087.png","license":0,"flickr_url":"","coco_url":"","date_captured":0},{"id":89,"width":640,"height":640,"file_name":"frame_000088.png","license":0,"flickr_url":"","coco_url":"","date_captured":0},{"id":90,"width":640,"height":640,"file_name":"frame_000089.png","license":0,"flickr_url":"","coco_url":"","date_captured":0},{"id":91,"width":640,"height":640,"file_name":"frame_000090.png","license":0,"flickr_url":"","coco_url":"","date_captured":0},{"id":92,"width":640,"height":640,"file_name":"frame_000091.png","license":0,"flickr_url":"","coco_url":"","date_captured":0},{"id":93,"width":640,"height":640,"file_name":"frame_000092.png","license":0,"flickr_url":"","coco_url":"","date_captured":0},{"id":94,"width":640,"height":640,"file_name":"frame_000093.png","license":0,"flickr_url":"","coco_url":"","date_captured":0},{"id":95,"width":640,"height":640,"file_name":"frame_000094.png","license":0,"flickr_url":"","coco_url":"","date_captured":0},{"id":96,"width":640,"height":640,"file_name":"frame_000095.png","license":0,"flickr_url":"","coco_url":"","date_captured":0},{"id":97,"width":640,"height":640,"file_name":"frame_000096.png","license":0,"flickr_url":"","coco_url":"","date_captured":0},{"id":98,"width":640,"height":640,"file_name":"frame_000097.png","license":0,"flickr_url":"","coco_url":"","date_captured":0},{"id":99,"width":640,"height":640,"file_name":"frame_000098.png","license":0,"flickr_url":"","coco_url":"","date_captured":0},{"id":100,"width":640,"height":640,"file_name":"frame_000099.png","license":0,"flickr_url":"","coco_url":"","date_captured":0}],"annotations":[{"id":1,"image_id":1,"category_id":19,"segmentation":[],"area":84463.836,"bbox":[234.59,78.67,179.94,469.4],"iscrowd":0,"attributes":{"occluded":false,"track_id":0,"keyframe":true},"keypoints":[331.23,104.82,2,345.23,78.67,2,313.49,80.94,2,365.61,90.6,2,299.42,105.5,2,376.84,149.18,2,311.45,174.71,2,414.53,177.14,1,282.74,259.51,2,408.32,127.83,1,234.59,237.41,2,400.92,275.64,2,341.96,307.1,2,392.52,400.41,1,296.96,400.41,2,386.02,532.39,1,290.9,548.07,2],"num_keypoints":17},{"id":2,"image_id":2,"category_id":19,"segmentation":[],"area":84514.21919999999,"bbox":[234.95,78.35,179.94,469.68],"iscrowd":0,"attributes":{"occluded":false,"track_id":0,"keyframe":false},"keypoints":[331.99,104.82,2,345.99,78.35,2,314.07,80.9,2,366.19,90.42,2,300.14,105.68,2,377.38,148.82,2,312.75,174.08,2,414.89,177.09,1,283.5,259.02,2,408.68,127.79,1,234.95,237.37,2,401.54,275.91,2,342.77,307.37,2,392.88,400.36,1,297.22,400.77,2,386.38,532.34,1,291.26,548.03,2],"num_keypoints":17},{"id":3,"image_id":3,"category_id":19,"segmentation":[],"area":84561.0036,"bbox":[235.31,78.04,179.94,469.94],"iscrowd":0,"attributes":{"occluded":false,"track_id":0,"keyframe":false},"keypoints":[332.76,104.82,2,346.76,78.04,2,314.65,80.85,2,366.78,90.25,2,300.86,105.86,2,377.92,148.46,2,314.05,173.45,2,415.25,177.05,1,284.27,258.53,2,409.04,127.74,1,235.31,237.32,2,402.17,276.18,2,343.58,307.64,2,393.23,400.32,1,297.49,401.12,2,386.74,532.3,1,291.62,547.98,2],"num_keypoints":17},{"id":4,"image_id":4,"category_id":19,"segmentation":[],"area":84614.28950000001,"bbox":[235.66,77.73,179.95,470.21],"iscrowd":0,"attributes":{"occluded":false,"track_id":0,"keyframe":false},"keypoints":[333.52,104.82,2,347.52,77.73,2,315.23,80.81,2,367.36,90.07,2,301.58,106.04,2,378.45,148.1,2,315.34,172.83,2,415.61,177.0,1,285.03,258.04,2,409.4,127.7,1,235.66,237.28,2,402.8,276.45,2,344.38,307.91,2,393.59,400.27,1,297.76,401.48,2,387.1,532.25,1,291.98,547.94,2],"num_keypoints":17},{"id":5,"image_id":5,"category_id":19,"segmentation":[],"area":84662.87600000002,"bbox":[236.02,77.41,179.95,470.48],"iscrowd":0,"attributes":{"occluded":false,"track_id":0,"keyframe":false},"keypoints":[334.28,104.82,2,348.28,77.41,2,315.82,80.76,2,367.94,89.89,2,302.29,106.22,2,378.99,147.74,2,316.64,172.2,2,415.97,176.96,1,285.79,257.54,2,409.75,127.65,1,236.02,237.23,2,403.43,276.72,2,345.19,308.18,2,393.95,400.23,1,298.03,401.84,2,387.46,532.21,1,292.34,547.89,2],"num_keypoints":17},{"id":6,"image_id":6,"category_id":19,"segmentation":[],"area":84711.4625,"bbox":[236.38,77.1,179.95,470.75],"iscrowd":0,"attributes":{"occluded":false,"track_id":0,"keyframe":false},"keypoints":[335.04,104.82,2,349.04,77.1,2,316.4,80.72,2,368.52,89.71,2,303.01,106.39,2,379.53,147.38,2,317.94,171.57,2,416.33,176.91,1,286.55,257.05,2,410.11,127.61,1,236.38,237.19,2,404.05,276.99,2,346.0,308.45,2,394.31,400.18,1,298.3,402.2,2,387.82,532.16,1,292.69,547.85,2],"num_keypoints":17},{"id":7,"image_id":7,"category_id":19,"segmentation":[],"area":84755.3388,"bbox":[236.74,76.78,179.94,471.02],"iscrowd":0,"attributes":{"occluded":false,"track_id":0,"keyframe":false},"keypoints":[335.8,104.82,2,349.8,76.78,2,316.98,80.67,2,369.11,89.53,2,303.73,106.57,2,380.07,147.03,2,319.24,170.94,2,416.68,176.87,1,287.31,256.56,2,410.47,127.56,1,236.74,237.14,2,404.68,277.26,2,346.8,308.72,2,394.67,400.14,1,298.57,402.56,2,388.17,532.12,1,293.05,547.8,2],"num_keypoints":17},{"id":8,"image_id":8,"category_id":19,"segmentation":[],"area":84803.9226,"bbox":[237.1,76.47,179.94,471.29],"iscrowd":0,"attributes":{"occluded":false,"track_id":0,"keyframe":false},"keypoints":[336.57,104.82,2,350.57,76.47,2,317.56,80.63,2,369.69,89.35,2,304.44,106.75,2,380.6,146.67,2,320.54,170.32,2,417.04,176.83,1,288.07,256.06,2,410.83,127.52,1,237.1,237.1,2,405.31,277.52,2,347.61,308.99,2,395.03,400.09,1,298.84,402.92,2,388.53,532.07,1,293.41,547.76,2],"num_keypoints":17},{"id":9,"image_id":9,"category_id":19,"segmentation":[],"area":84850.707,"bbox":[237.46,76.16,179.94,471.55],"iscrowd":0,"attributes":{"occluded":false,"track_id":0,"keyframe":false},"keypoints":[337.33,104.82,2,351.33,76.16,2,318.15,80.58,2,370.27,89.17,2,305.16,106.93,2,381.14,146.31,2,321.84,169.69,2,417.4,176.78,1,288.84,255.57,2,411.19,127.47,1,237.46,237.05,2,405.94,277.79,2,348.42,309.26,2,395.39,400.05,1,299.11,403.28,2,388.89,532.03,1,293.77,547.71,2],"num_keypoints":17},{"id":10,"image_id":10,"category_id":19,"segmentation":[],"area":84901.09019999999,"bbox":[237.82,75.84,179.94,471.83],"iscrowd":0,"attributes":{"occluded":false,"track_id":0,"keyframe":false},"keypoints":[338.09,104.82,2,352.09,75.84,2,318.73,80.54,2,370.86,88.99,2,305.88,107.11,2,381.68,145.95,2,323.14,169.06,2,417.76,176.74,1,289.6,255.08,2,411.55,127.43,1,237.82,237.01,2,406.56,278.06,2,349.22,309.52,2,395.74,400.0,1,299.38,403.63,2,389.25,531.98,1,294.13,547.67,2],"num_keypoints":17},{"id":11,"image_id":11,"category_id":19,"segmentation":[],"area":84952.59550000001,"bbox":[238.17,75.53,179.95,472.09],"iscrowd":0,"attributes":{"occluded":false,"track_id":0,"keyframe":true},"keypoints":[338.85,104.82,2,352.85,75.53,2,319.31,80.49,2,371.44,88.81,2,306.59,107.29,2,382.22,145.59,2,324.44,168.43,2,418.12,176.69,1,290.36,254.58,2,411.91,127.38,1,238.17,236.97,2,407.19,278.33,2,350.03,309.79,2,396.1,399.96,1,299.64,403.99,2,389.61,531.94,1,294.49,547.62,2],"num_keypoints":17},{"id":12,"image_id":12,"category_id":19,"segmentation":[],"area":85001.18200000002,"bbox":[238.53,75.22,179.95,472.36],"iscrowd":0,"attributes":{"occluded":false,"track_id":0,"keyframe":false},"keypoints":[339.61,104.82,2,353.61,75.22,2,319.9,80.45,2,372.02,88.63,2,307.31,107.47,2,382.76,145.23,2,325.74,167.81,2,418.48,176.65,1,291.12,254.09,2,412.26,127.34,1,238.53,236.92,2,406.83,277.35,2,350.21,308.18,2,396.46,399.91,1,300.36,403.9,2,389.97,531.89,1,294.85,547.58,2],"num_keypoints":17},{"id":13,"image_id":13,"category_id":19,"segmentation":[],"area":85045.0422,"bbox":[238.89,74.9,179.94,472.63],"iscrowd":0,"attributes":{"occluded":false,"track_id":0,"keyframe":false},"keypoints":[340.38,104.82,2,354.38,74.9,2,320.48,80.4,2,372.6,88.45,2,308.03,107.65,2,383.29,144.87,2,327.04,167.18,2,418.83,176.6,1,291.88,253.6,2,412.62,127.3,1,238.89,236.88,2,406.47,276.36,2,350.39,306.57,2,396.82,399.87,1,301.08,403.81,2,390.33,531.85,1,295.2,547.53,2],"num_keypoints":17},{"id":14,"image_id":14,"category_id":19,"segmentation":[],"area":85093.62599999999,"bbox":[239.25,74.59,179.94,472.9],"iscrowd":0,"attributes":{"occluded":false,"track_id":0,"keyframe":false},"keypoints":[341.14,104.82,2,355.14,74.59,2,321.06,80.36,2,373.19,88.27,2,308.75,107.83,2,383.83,144.52,2,328.34,166.55,2,419.19,176.56,1,292.65,253.11,2,412.98,127.25,1,239.25,236.83,2,406.11,275.37,2,350.57,304.95,2,397.18,399.82,1,301.8,403.72,2,390.68,531.8,1,295.56,547.49,2],"num_keypoints":17},{"id":15,"image_id":15,"category_id":19,"segmentation":[],"area":85142.20980000001,"bbox":[239.61,74.27,179.94,473.17],"iscrowd":0,"attributes":{"occluded":false,"track_id":0,"keyframe":false},"keypoints":[341.9,104.82,2,355.9,74.27,2,321.64,80.31,2,373.77,88.09,2,309.46,108.01,2,384.37,144.16,2,329.64,165.92,2,419.55,176.51,1,293.41,252.61,2,413.34,127.21,1,239.61,236.79,2,405.76,274.39,2,350.75,303.34,2,397.54,399.78,1,302.51,403.63,2,391.04,531.76,1,295.92,547.44,2],"num_keypoints":17},{"id":16,"image_id":16,"category_id":19,"segmentation":[],"area":85190.79360000002,"bbox":[239.97,73.96,179.94,473.44],"iscrowd":0,"attributes":{"occluded":false,"track_id":0,"keyframe":false},"keypoints":[342.66,104.82,2,356.66,73.96,2,322.23,80.27,2,374.35,87.91,2,310.18,108.19,2,384.91,143.8,2,330.94,165.3,2,419.91,176.47,1,294.17,252.12,2,413.7,127.16,1,239.97,236.74,2,405.4,273.4,2,350.93,301.73,2,397.9,399.73,1,303.23,403.55,2,391.4,531.71,1,296.28,547.4,2],"num_keypoints":17},{"id":17,"image_id":17,"category_id":19,"segmentation":[],"area":85239.3774,"bbox":[240.33,73.65,179.94,473.71],"iscrowd":0,"attributes":{"occluded":false,"track_id":0,"keyframe":false},"keypoints":[343.42,104.82,2,357.42,73.65,2,322.81,80.22,2,374.93,87.74,2,310.9,108.37,2,385.44,143.44,2,332.24,164.67,2,420.27,176.42,1,294.93,251.63,2,414.06,127.12,1,240.33,236.7,2,405.04,272.42,2,351.11,300.11,2,398.25,399.69,1,303.95,403.46,2,391.76,531.67,1,296.64,547.36,2],"num_keypoints":17},{"id":18,"image_id":18,"category_id":19,"segmentation":[],"area":85292.70099999999,"bbox":[240.68,73.33,179.95,473.98],"iscrowd":0,"attributes":{"occluded":false,"track_id":0,"keyframe":false},"keypoints":[344.18,104.82,2,358.19,73.33,2,323.39,80.18,2,375.52,87.56,2,311.61,108.55,2,385.98,143.08,2,333.54,164.04,2,420.63,176.38,1,295.69,251.13,2,414.42,127.07,1,240.68,236.65,2,404.68,271.43,2,351.29,298.5,2,398.61,399.65,1,304.66,403.37,2,392.12,531.62,1,297.0,547.31,2],"num_keypoints":17},{"id":19,"image_id":19,"category_id":19,"segmentation":[],"area":85341.2875,"bbox":[241.04,73.02,179.95,474.25],"iscrowd":0,"attributes":{"occluded":false,"track_id":0,"keyframe":false},"keypoints":[344.95,104.82,2,358.95,73.02,2,323.97,80.13,2,376.1,87.38,2,312.33,108.72,2,386.52,142.72,2,334.84,163.41,2,420.99,176.33,1,296.46,250.64,2,414.77,127.03,1,241.04,236.61,2,404.32,270.44,2,351.46,296.89,2,398.97,399.6,1,305.38,403.28,2,392.48,531.58,1,297.36,547.27,2],"num_keypoints":17},{"id":20,"image_id":20,"category_id":19,"segmentation":[],"area":85383.32939999999,"bbox":[241.4,72.71,179.94,474.51],"iscrowd":0,"attributes":{"occluded":false,"track_id":0,"keyframe":false},"keypoints":[345.71,104.82,2,359.71,72.71,2,324.56,80.09,2,376.68,87.2,2,313.05,108.9,2,387.06,142.37,2,336.14,162.79,2,421.34,176.29,1,297.22,250.15,2,415.13,126.98,1,241.4,236.56,2,403.96,269.46,2,351.64,295.27,2,399.33,399.56,1,306.1,403.19,2,392.83,531.53,1,297.71,547.22,2],"num_keypoints":17},{"id":21,"image_id":21,"category_id":19,"segmentation":[],"area":85433.7126,"bbox":[241.76,72.39,179.94,474.79],"iscrowd":0,"attributes":{"occluded":false,"track_id":0,"keyframe":true},"keypoints":[346.47,104.82,2,360.47,72.39,2,325.14,80.04,2,377.26,87.02,2,313.77,109.08,2,387.6,142.01,2,337.44,162.16,2,421.7,176.24,1,297.98,249.65,2,415.49,126.94,1,241.76,236.52,2,403.6,268.47,2,351.82,293.66,2,399.69,399.51,1,306.81,403.1,2,393.19,531.49,1,298.07,547.18,2],"num_keypoints":17},{"id":22,"image_id":22,"category_id":19,"segmentation":[],"area":85431.91319999998,"bbox":[239.34,73.11,179.94,474.78],"iscrowd":0,"attributes":{"occluded":false,"track_id":0,"keyframe":false},"keypoints":[344.05,105.54,2,358.05,73.11,2,322.72,80.76,2,374.84,87.74,2,311.35,109.8,2,386.7,142.1,2,334.3,162.34,2,419.28,176.96,1,296.81,250.01,2,413.07,127.65,1,239.34,237.23,2,403.07,268.11,2,350.93,293.3,2,397.27,400.23,1,304.39,403.81,2,390.77,532.21,1,295.65,547.89,2],"num_keypoints":17},{"id":23,"image_id":23,"category_id":19,"segmentation":[],"area":85431.91320000002,"bbox":[236.92,73.83,179.94,474.78],"iscrowd":0,"attributes":{"occluded":false,"track_id":0,"keyframe":false},"keypoints":[341.63,106.26,2,355.63,73.83,2,320.3,81.48,2,372.42,88.45,2,308.93,110.52,2,385.8,142.19,2,331.17,162.52,2,416.86,177.68,1,295.65,250.37,2,410.65,128.37,1,236.92,237.95,2,402.53,267.76,2,350.03,292.94,2,394.85,400.94,1,301.97,404.53,2,388.35,532.92,1,293.23,548.61,2],"num_keypoints":17},{"id":24,"image_id":24,"category_id":19,"segmentation":[],"area":85433.7126,"bbox":[234.5,74.54,179.94,474.79],"iscrowd":0,"attributes":{"occluded":false,"track_id":0,"keyframe":false},"keypoints":[339.21,106.98,2,353.21,74.54,2,317.88,82.2,2,370.0,89.17,2,306.51,111.23,2,384.91,142.28,2,328.03,162.7,2,414.44,178.39,1,294.48,250.73,2,408.23,129.09,1,234.5,238.67,2,401.99,267.4,2,349.14,292.58,2,392.43,401.66,1,299.55,405.25,2,385.93,533.64,1,290.81,549.33,2],"num_keypoints":17},{"id":25,"image_id":25,"category_id":19,"segmentation":[],"area":85431.91319999998,"bbox":[232.08,75.26,179.94,474.78],"iscrowd":0,"attributes":{"occluded":false,"track_id":0,"keyframe":false},"keypoints":[336.79,107.69,2,350.79,75.26,2,315.46,82.91,2,367.58,89.89,2,304.09,111.95,2,384.01,142.37,2,324.89,162.88,2,412.02,179.11,1,293.32,251.09,2,405.81,129.8,1,232.08,239.38,2,401.45,267.04,2,348.24,292.23,2,390.01,402.38,1,297.13,405.97,2,383.51,534.36,1,288.39,550.04,2],"num_keypoints":17},{"id":26,"image_id":26,"category_id":19,"segmentation":[],"area":85431.91320000001,"bbox":[229.66,75.98,179.94,474.78],"iscrowd":0,"attributes":{"occluded":false,"track_id":0,"keyframe":false},"keypoints":[334.37,108.41,2,348.37,75.98,2,313.04,83.63,2,365.16,90.6,2,301.67,112.67,2,383.11,142.46,2,321.75,163.06,2,409.6,179.83,1,292.15,251.45,2,403.39,130.52,1,229.66,240.1,2,400.92,266.68,2,347.34,291.87,2,387.59,403.1,1,294.71,406.68,2,381.09,535.07,1,285.97,550.76,2],"num_keypoints":17},{"id":27,"image_id":27,"category_id":19,"segmentation":[],"area":85431.91320000001,"bbox":[227.24,76.7,179.94,474.78],"iscrowd":0,"attributes":{"occluded":false,"track_id":0,"keyframe":false},"keypoints":[331.95,109.13,2,345.95,76.7,2,310.62,84.35,2,362.74,91.32,2,299.24,113.39,2,382.22,142.54,2,318.62,163.24,2,407.18,180.54,1,290.99,251.81,2,400.97,131.24,1,227.24,240.82,2,400.38,266.32,2,346.45,291.51,2,385.17,403.81,1,292.29,407.4,2,378.67,535.79,1,283.55,551.48,2],"num_keypoints":17},{"id":28,"image_id":28,"category_id":19,"segmentation":[],"area":85433.71260000001,"bbox":[224.82,77.41,179.94,474.79],"iscrowd":0,"attributes":{"occluded":false,"track_id":0,"keyframe":false},"keypoints":[329.53,109.84,2,343.53,77.41,2,308.2,85.06,2,360.32,92.04,2,296.82,114.1,2,381.32,142.63,2,315.48,163.41,2,404.76,181.26,1,289.82,252.16,2,398.55,131.96,1,224.82,241.54,2,399.84,265.96,2,345.55,291.15,2,382.75,404.53,1,289.87,408.12,2,376.25,536.51,1,281.13,552.2,2],"num_keypoints":17},{"id":29,"image_id":29,"category_id":19,"segmentation":[],"area":85431.91319999998,"bbox":[222.4,78.13,179.94,474.78],"iscrowd":0,"attributes":{"occluded":false,"track_id":0,"keyframe":false},"keypoints":[327.11,110.56,2,341.11,78.13,2,305.78,85.78,2,357.9,92.76,2,294.4,114.82,2,380.43,142.72,2,312.34,163.59,2,402.34,181.98,1,288.66,252.52,2,396.13,132.67,1,222.4,242.25,2,399.3,265.6,2,344.65,290.79,2,380.33,405.25,1,287.45,408.83,2,373.83,537.23,1,278.71,552.91,2],"num_keypoints":17},{"id":30,"image_id":30,"category_id":19,"segmentation":[],"area":85431.91320000001,"bbox":[219.98,78.85,179.94,474.78],"iscrowd":0,"attributes":{"occluded":false,"track_id":0,"keyframe":false},"keypoints":[324.69,111.28,2,338.69,78.85,2,303.36,86.5,2,355.48,93.47,2,291.98,115.54,2,379.53,142.81,2,309.21,163.77,2,399.92,182.7,1,287.49,252.88,2,393.71,133.39,1,219.98,242.97,2,398.77,265.25,2,343.76,290.43,2,377.91,405.96,1,285.03,409.55,2,371.41,537.94,1,276.29,553.63,2],"num_keypoints":17},{"id":31,"image_id":31,"category_id":19,"segmentation":[],"area":85780.30930000001,"bbox":[217.56,79.56,180.67,474.79],"iscrowd":0,"attributes":{"occluded":false,"track_id":0,"keyframe":true},"keypoints":[322.27,112.0,2,336.27,79.56,2,300.94,87.21,2,353.06,94.19,2,289.56,116.25,2,378.63,142.9,2,306.07,163.95,2,397.5,183.41,1,286.33,253.24,2,391.29,134.11,1,217.56,243.69,2,398.23,264.89,2,342.86,290.07,2,375.49,406.68,1,282.61,410.27,2,368.99,538.66,1,273.87,554.35,2],"num_keypoints":17},{"id":32,"image_id":32,"category_id":19,"segmentation":[],"area":85733.8866,"bbox":[216.84,80.46,180.03,476.22],"iscrowd":0,"attributes":{"occluded":false,"track_id":0,"keyframe":false},"keypoints":[318.42,112.89,2,332.42,80.46,2,297.08,88.11,2,349.21,95.09,2,285.71,117.15,2,374.78,143.8,2,302.21,164.85,2,396.87,188.34,1,283.82,254.23,2,390.39,137.51,1,216.84,244.23,2,396.26,264.8,2,341.16,290.43,2,375.49,408.21,1,283.06,411.88,2,369.8,538.93,1,275.75,556.68,2],"num_keypoints":17},{"id":33,"image_id":33,"category_id":19,"segmentation":[],"area":86039.09449999999,"bbox":[216.12,81.36,180.13,477.65],"iscrowd":0,"attributes":{"occluded":false,"track_id":0,"keyframe":false},"keypoints":[314.56,113.79,2,328.56,81.36,2,293.23,89.01,2,345.35,95.98,2,281.86,118.05,2,370.92,144.7,2,298.36,165.75,2,396.25,193.27,1,281.31,255.21,2,389.5,140.92,1,216.12,244.76,2,394.28,264.71,2,339.46,290.79,2,375.49,409.73,1,283.51,413.49,2,370.61,539.2,1,277.64,559.01,2],"num_keypoints":17},{"id":34,"image_id":34,"category_id":19,"segmentation":[],"area":86336.8089,"bbox":[215.41,82.25,180.21,479.09],"iscrowd":0,"attributes":{"occluded":false,"track_id":0,"keyframe":false},"keypoints":[310.71,114.68,2,324.71,82.25,2,289.37,89.9,2,341.5,96.88,2,278.0,118.94,2,367.07,145.59,2,294.51,166.64,2,395.62,198.2,1,278.8,256.2,2,388.6,144.33,1,215.41,245.3,2,392.31,264.62,2,337.75,291.15,2,375.49,411.25,1,283.96,415.11,2,371.41,539.47,1,279.52,561.34,2],"num_keypoints":17},{"id":35,"image_id":35,"category_id":19,"segmentation":[],"area":86637.75600000001,"bbox":[214.69,83.15,180.3,480.52],"iscrowd":0,"attributes":{"occluded":false,"track_id":0,"keyframe":false},"keypoints":[306.85,115.58,2,320.85,83.15,2,285.52,90.8,2,337.64,97.78,2,274.15,119.84,2,363.22,146.49,2,290.65,167.54,2,394.99,203.13,1,276.29,257.18,2,387.7,147.73,1,214.69,245.84,2,390.34,264.53,2,336.05,291.51,2,375.49,412.78,1,284.41,416.72,2,372.22,539.74,1,281.4,563.67,2],"num_keypoints":17},{"id":36,"image_id":36,"category_id":19,"segmentation":[],"area":86938.9605,"bbox":[213.97,84.05,180.39,481.95],"iscrowd":0,"attributes":{"occluded":false,"track_id":0,"keyframe":false},"keypoints":[303.0,116.48,2,317.0,84.05,2,281.67,91.7,2,333.79,98.67,2,270.29,120.74,2,359.36,147.39,2,286.8,168.43,2,394.36,208.06,1,273.78,258.17,2,386.81,151.14,1,213.97,246.38,2,388.37,264.44,2,334.35,291.87,2,375.49,414.3,1,284.85,418.34,2,373.03,540.01,1,283.28,566.0,2],"num_keypoints":17},{"id":37,"image_id":37,"category_id":19,"segmentation":[],"area":87242.22720000002,"bbox":[213.26,84.94,180.48,483.39],"iscrowd":0,"attributes":{"occluded":false,"track_id":0,"keyframe":false},"keypoints":[299.14,117.37,2,313.14,84.94,2,277.81,92.59,2,329.94,99.57,2,266.44,121.63,2,355.51,148.28,2,282.94,169.33,2,393.74,212.99,1,271.27,259.16,2,385.91,154.54,1,213.26,246.91,2,386.4,264.35,2,332.64,292.23,2,375.49,415.83,1,285.3,419.95,2,373.83,540.27,1,285.16,568.33,2],"num_keypoints":17},{"id":38,"image_id":38,"category_id":19,"segmentation":[],"area":87543.9474,"bbox":[212.54,85.84,180.57,484.82],"iscrowd":0,"attributes":{"occluded":false,"track_id":0,"keyframe":false},"keypoints":[295.29,118.27,2,309.29,85.84,2,273.96,93.49,2,326.08,100.46,2,262.58,122.53,2,351.65,149.18,2,279.09,170.23,2,393.11,217.92,1,268.76,260.14,2,385.01,157.95,1,212.54,247.45,2,384.42,264.26,2,330.94,292.58,2,375.49,417.35,1,285.75,421.56,2,374.64,540.54,1,287.05,570.66,2],"num_keypoints":17},{"id":39,"image_id":39,"category_id":19,"segmentation":[],"area":87847.73160000001,"bbox":[211.82,86.73,180.66,486.26],"iscrowd":0,"attributes":{"occluded":false,"track_id":0,"keyframe":false},"keypoints":[291.43,119.17,2,305.43,86.73,2,270.1,94.39,2,322.23,101.36,2,258.73,123.42,2,347.8,150.07,2,275.23,171.12,2,392.48,222.85,1,266.25,261.13,2,384.12,161.36,1,211.82,247.99,2,382.45,264.17,2,329.24,292.94,2,375.49,418.87,1,286.2,423.18,2,375.44,540.81,1,288.93,572.99,2],"num_keypoints":17},{"id":40,"image_id":40,"category_id":19,"segmentation":[],"area":88154.84440000002,"bbox":[211.1,87.63,180.76,487.69],"iscrowd":0,"attributes":{"occluded":false,"track_id":0,"keyframe":false},"keypoints":[287.58,120.06,2,301.58,87.63,2,266.25,95.28,2,318.37,102.26,2,254.87,124.32,2,343.94,150.97,2,271.38,172.02,2,391.86,227.78,1,263.74,262.11,2,383.22,164.76,1,211.1,248.53,2,380.48,264.08,2,327.53,293.3,2,375.49,420.4,1,286.65,424.79,2,376.25,541.08,1,290.81,575.32,2],"num_keypoints":17},{"id":41,"image_id":41,"category_id":19,"segmentation":[],"area":88452.46080000002,"bbox":[210.39,88.53,180.84,489.12],"iscrowd":0,"attributes":{"occluded":false,"track_id":0,"keyframe":true},"keypoints":[283.73,120.96,2,297.73,88.53,2,262.39,96.18,2,314.52,103.15,2,251.02,125.22,2,340.09,151.87,2,267.52,172.92,2,391.23,232.71,2,261.23,263.1,2,382.33,168.17,1,210.39,249.07,2,378.51,263.99,2,325.83,293.66,2,375.49,421.92,1,287.09,426.4,2,377.06,541.35,1,292.69,577.65,2],"num_keypoints":17},{"id":42,"image_id":42,"category_id":1,"segmentation":[],"area":97274.73359999998,"bbox":[203.93,105.87,212.08,458.67],"iscrowd":0,"attributes":{"occluded":false,"track_id":1,"keyframe":true},"keypoints":[281.58,134.72,1,292.01,105.87,1,263.29,110.38,1,304.33,119.22,1,252.05,136.19,1,330.06,161.44,2,273.62,183.04,2,385.91,226.63,2,255.39,263.83,2,392.65,184.11,1,203.93,249.89,2,382.27,274.27,2,326.82,307.43,2,403.03,427.0,1,300.82,445.64,2,416.01,531.47,1,295.92,564.54,2],"num_keypoints":17},{"id":43,"image_id":43,"category_id":1,"segmentation":[],"area":100229.44080000001,"bbox":[201.6,109.33,220.12,455.34],"iscrowd":0,"attributes":{"occluded":false,"track_id":1,"keyframe":false},"keypoints":[272.75,138.36,1,281.95,109.33,1,253.65,114.94,1,294.7,122.08,1,243.51,140.98,1,322.6,163.3,2,266.76,186.6,2,382.45,226.57,2,253.2,267.1,2,385.23,183.87,1,201.6,253.68,2,378.66,274.16,2,325.86,307.62,2,404.72,423.49,1,299.33,445.01,2,421.72,526.61,1,295.3,564.67,2],"num_keypoints":17},{"id":44,"image_id":44,"category_id":1,"segmentation":[],"area":103128.36299999998,"bbox":[199.28,112.79,228.15,452.02],"iscrowd":0,"attributes":{"occluded":false,"track_id":1,"keyframe":false},"keypoints":[263.91,141.99,1,271.9,112.79,1,244.0,119.49,1,285.07,124.95,1,234.97,145.77,1,315.15,165.17,2,259.89,190.15,2,378.99,226.52,2,251.01,270.36,2,377.8,183.63,1,199.28,257.47,2,375.05,274.05,2,324.9,307.81,2,406.42,419.98,1,297.84,444.39,2,427.43,521.74,1,294.68,564.81,2],"num_keypoints":17},{"id":45,"image_id":45,"category_id":1,"segmentation":[],"area":105971.6042,"bbox":[196.96,116.25,236.18,448.69],"iscrowd":0,"attributes":{"occluded":false,"track_id":1,"keyframe":false},"keypoints":[255.08,145.63,1,261.84,116.25,1,234.36,124.04,1,275.44,127.81,1,226.44,150.55,1,307.69,167.04,2,253.03,193.71,2,375.53,226.47,2,248.82,273.63,2,370.37,183.38,1,196.96,261.26,2,371.44,273.93,2,323.94,308.0,2,408.12,416.47,1,296.35,443.77,2,433.14,516.87,1,294.06,564.94,2],"num_keypoints":17},{"id":46,"image_id":46,"category_id":1,"segmentation":[],"area":108768.26140000003,"bbox":[194.63,119.7,244.22,445.37],"iscrowd":0,"attributes":{"occluded":false,"track_id":1,"keyframe":false},"keypoints":[246.25,149.27,1,251.79,119.7,1,224.71,128.6,1,265.81,130.68,1,217.9,155.34,1,300.24,168.91,2,246.16,197.27,2,372.08,226.42,2,246.63,276.89,2,362.94,183.14,1,194.63,265.05,2,367.83,273.82,2,322.98,308.18,2,409.82,412.96,1,294.86,443.15,2,438.85,512.0,1,293.43,565.07,2],"num_keypoints":17},{"id":47,"image_id":47,"category_id":1,"segmentation":[],"area":111504.59000000003,"bbox":[192.31,123.16,252.25,442.04],"iscrowd":0,"attributes":{"occluded":false,"track_id":1,"keyframe":false},"keypoints":[237.41,152.9,1,241.74,123.16,1,215.07,133.15,1,256.19,133.54,1,209.36,160.13,1,292.78,170.78,2,239.3,200.83,2,368.62,226.37,2,244.44,280.16,2,355.52,182.9,1,192.31,268.85,2,364.21,273.7,2,322.02,308.37,2,411.52,409.44,1,293.37,442.53,2,444.56,507.13,1,292.81,565.2,2],"num_keypoints":17},{"id":48,"image_id":48,"category_id":1,"segmentation":[],"area":114194.4288,"bbox":[189.98,126.62,260.29,438.72],"iscrowd":0,"attributes":{"occluded":false,"track_id":1,"keyframe":false},"keypoints":[228.58,156.54,1,231.68,126.62,1,205.43,137.7,1,246.56,136.41,1,200.82,164.92,1,285.33,172.65,2,232.43,204.39,2,365.16,226.31,2,242.25,283.42,2,348.09,182.66,1,189.98,272.64,2,360.6,273.59,2,321.06,308.56,2,413.22,405.93,1,291.88,441.9,2,450.27,502.27,1,292.19,565.34,2],"num_keypoints":17},{"id":49,"image_id":49,"category_id":1,"segmentation":[],"area":116823.84480000002,"bbox":[187.66,130.08,268.32,435.39],"iscrowd":0,"attributes":{"occluded":false,"track_id":1,"keyframe":false},"keypoints":[219.75,160.17,1,221.63,130.08,1,195.78,142.26,1,236.93,139.27,1,192.29,169.7,1,277.87,174.52,2,225.56,207.95,2,361.71,226.26,2,240.06,286.69,2,340.66,182.41,1,187.66,276.43,2,356.99,273.47,2,320.09,308.75,2,414.92,402.42,1,290.38,441.28,2,455.98,497.4,1,291.57,565.47,2],"num_keypoints":17},{"id":50,"image_id":50,"category_id":1,"segmentation":[],"area":120082.43580000002,"bbox":[183.75,133.54,277.93,432.06],"iscrowd":0,"attributes":{"occluded":false,"track_id":1,"keyframe":false},"keypoints":[210.91,163.81,1,211.57,133.54,1,186.14,146.81,1,227.3,142.14,1,183.75,174.49,1,270.41,176.39,2,218.7,211.51,2,358.25,226.21,2,237.87,289.95,2,333.24,182.17,1,185.34,280.22,2,353.38,273.36,2,319.13,308.94,2,416.62,398.91,1,288.89,440.66,2,461.68,492.53,1,290.95,565.6,2],"num_keypoints":17},{"id":51,"image_id":51,"category_id":1,"segmentation":[],"area":125269.25319999998,"bbox":[175.21,137.0,292.18,428.74],"iscrowd":0,"attributes":{"occluded":false,"track_id":1,"keyframe":false},"keypoints":[202.08,167.45,1,201.52,137.0,1,176.49,151.36,1,217.67,145.0,1,175.21,179.28,1,262.96,178.25,2,211.83,215.07,2,354.79,226.16,2,235.67,293.22,2,325.81,181.93,1,183.01,284.01,2,349.76,273.24,2,318.17,309.12,2,418.31,395.4,1,287.4,440.04,2,467.39,487.66,1,290.32,565.74,2],"num_keypoints":17},{"id":52,"image_id":52,"category_id":1,"segmentation":[],"area":130354.1322,"bbox":[166.68,140.46,306.42,425.41],"iscrowd":0,"attributes":{"occluded":false,"track_id":1,"keyframe":true},"keypoints":[193.25,171.08,1,191.46,140.46,1,166.85,155.92,1,208.05,147.87,1,166.68,184.07,1,255.5,180.12,2,204.97,218.62,2,351.33,226.11,2,233.48,296.48,2,318.38,181.69,2,180.69,287.81,1,346.15,273.13,2,317.21,309.31,2,420.01,391.89,1,285.91,439.41,2,473.1,482.79,1,289.7,565.87,2],"num_keypoints":17},{"id":53,"image_id":53,"category_id":1,"segmentation":[],"area":131770.00069999998,"bbox":[160.05,145.59,313.91,419.77],"iscrowd":0,"attributes":{"occluded":false,"track_id":1,"keyframe":false},"keypoints":[186.75,176.06,1,184.16,145.59,1,160.05,161.66,1,200.88,152.53,1,160.63,189.71,1,249.02,183.39,2,199.71,223.11,2,345.74,226.63,2,230.22,299.91,2,321.57,182.54,2,177.38,292.69,1,343.28,273.25,2,313.98,310.44,2,418.62,389.95,1,285.75,439.11,2,473.96,479.09,1,291.86,565.36,2],"num_keypoints":17},{"id":54,"image_id":54,"category_id":1,"segmentation":[],"area":133175.92539999998,"bbox":[153.24,150.72,321.58,414.13],"iscrowd":0,"attributes":{"occluded":false,"track_id":1,"keyframe":false},"keypoints":[180.26,181.03,1,176.85,150.72,1,153.24,167.39,1,193.7,157.19,1,154.59,195.35,1,242.55,186.65,2,194.45,227.59,2,340.15,227.15,2,226.95,303.34,2,324.77,183.39,2,174.07,297.57,1,340.4,273.38,2,310.75,311.57,2,417.23,388.01,1,285.6,438.81,2,474.82,475.39,1,294.01,564.85,2],"num_keypoints":17},{"id":55,"image_id":55,"category_id":1,"segmentation":[],"area":134487.9552,"bbox":[146.44,155.86,329.24,408.48],"iscrowd":0,"attributes":{"occluded":false,"track_id":1,"keyframe":false},"keypoints":[173.77,186.0,1,169.54,155.86,1,146.44,173.13,1,186.53,161.85,1,148.54,200.99,1,236.07,189.92,2,189.2,232.07,2,334.55,227.66,2,223.68,306.77,2,327.96,184.24,2,170.77,302.45,1,337.52,273.51,2,307.52,312.7,2,415.85,386.07,1,285.45,438.51,2,475.68,471.69,1,296.17,564.34,2],"num_keypoints":17},{"id":56,"image_id":56,"category_id":1,"segmentation":[],"area":135716.79600000003,"bbox":[139.64,160.99,336.9,402.84],"iscrowd":0,"attributes":{"occluded":false,"track_id":1,"keyframe":false},"keypoints":[167.28,190.97,1,162.23,160.99,1,139.64,178.87,1,179.36,166.51,1,142.5,206.62,1,229.59,193.18,2,183.94,236.55,2,328.96,228.18,2,220.41,310.2,2,331.15,185.09,2,167.46,307.33,1,334.65,273.63,2,304.29,313.83,2,414.46,384.13,1,285.29,438.21,2,476.54,467.99,1,298.33,563.83,2],"num_keypoints":17},{"id":57,"image_id":57,"category_id":1,"segmentation":[],"area":136859.232,"bbox":[132.84,166.12,344.56,397.2],"iscrowd":0,"attributes":{"occluded":false,"track_id":1,"keyframe":false},"keypoints":[160.79,195.95,1,154.92,166.12,1,132.84,184.61,1,172.19,171.17,1,136.45,212.26,1,223.11,196.45,2,178.69,241.04,2,323.36,228.7,2,217.15,313.63,2,334.34,185.94,2,164.16,312.21,1,331.77,273.76,2,301.05,314.96,2,413.07,382.19,1,285.14,437.91,2,477.4,464.29,1,300.48,563.32,2],"num_keypoints":17},{"id":58,"image_id":58,"category_id":1,"segmentation":[],"area":137915.65649999998,"bbox":[126.03,171.26,352.23,391.55],"iscrowd":0,"attributes":{"occluded":false,"track_id":1,"keyframe":false},"keypoints":[154.3,200.92,1,147.61,171.26,1,126.03,190.35,1,165.02,175.83,1,130.41,217.9,1,216.63,199.72,2,173.43,245.52,2,317.77,229.22,2,213.88,317.06,2,337.54,186.8,2,160.85,317.09,1,328.89,273.89,2,297.82,316.09,2,411.68,380.25,1,284.98,437.61,2,478.26,460.59,1,302.64,562.81,2],"num_keypoints":17},{"id":59,"image_id":59,"category_id":1,"segmentation":[],"area":138885.1499,"bbox":[119.23,176.39,359.89,385.91],"iscrowd":0,"attributes":{"occluded":false,"track_id":1,"keyframe":false},"keypoints":[147.8,205.89,1,140.3,176.39,1,119.23,196.09,1,157.85,180.49,1,124.37,223.54,1,210.16,202.98,2,168.17,250.0,2,312.17,229.74,2,210.61,320.49,2,340.73,187.65,2,157.54,321.97,1,326.02,274.01,2,294.59,317.22,2,410.29,378.31,1,284.83,437.31,2,479.12,456.88,1,304.8,562.3,2],"num_keypoints":17},{"id":60,"image_id":60,"category_id":1,"segmentation":[],"area":139768.2385,"bbox":[112.43,181.52,367.55,380.27],"iscrowd":0,"attributes":{"occluded":false,"track_id":1,"keyframe":false},"keypoints":[141.31,210.86,1,132.99,181.52,1,112.43,201.83,1,150.68,185.15,1,118.32,229.18,1,203.68,206.25,2,162.92,254.48,2,306.58,230.26,2,207.34,323.91,2,343.92,188.5,2,154.24,326.85,1,323.14,274.14,2,291.36,318.35,2,408.9,376.38,1,284.67,437.01,2,479.98,453.18,1,306.95,561.79,2],"num_keypoints":17},{"id":61,"image_id":61,"category_id":1,"segmentation":[],"area":140561.1702,"bbox":[105.63,186.66,375.21,374.62],"iscrowd":0,"attributes":{"occluded":false,"track_id":1,"keyframe":false},"keypoints":[134.82,215.84,1,125.69,186.66,1,105.63,207.56,1,143.51,189.81,1,112.28,234.82,1,197.2,209.51,2,157.66,258.97,2,300.99,230.78,2,204.08,327.34,2,347.11,189.35,2,150.93,331.73,1,320.26,274.26,2,288.13,319.48,2,407.51,374.44,1,284.52,436.71,2,480.84,449.48,1,309.11,561.28,2],"num_keypoints":17},{"id":62,"image_id":62,"category_id":1,"segmentation":[],"area":141880.1359,"bbox":[98.83,190.2,382.87,370.57],"iscrowd":0,"attributes":{"occluded":false,"track_id":1,"keyframe":true},"keypoints":[128.33,220.81,1,118.38,191.79,1,98.83,213.3,1,136.34,194.47,1,106.23,240.46,1,190.72,212.78,2,152.4,263.45,2,295.39,231.3,2,200.81,330.77,2,350.31,190.2,2,147.62,336.61,1,317.39,274.39,2,284.9,320.61,2,406.12,372.5,1,284.36,436.41,2,481.7,445.78,1,311.26,560.77,2],"num_keypoints":17},{"id":63,"image_id":63,"category_id":1,"segmentation":[],"area":138786.9888,"bbox":[98.56,192.26,380.28,364.96],"iscrowd":0,"attributes":{"occluded":false,"track_id":1,"keyframe":false},"keypoints":[126.89,231.66,1,117.66,203.35,1,98.56,224.95,1,134.91,205.32,1,104.8,251.31,1,189.38,225.59,2,151.6,276.45,2,292.43,238.38,2,197.59,345.88,2,348.69,192.26,2,145.65,349.62,1,315.5,287.3,2,281.4,333.34,2,405.4,376.62,1,278.45,442.95,2,478.84,441.3,1,307.79,557.22,2],"num_keypoints":17},{"id":64,"image_id":64,"category_id":1,"segmentation":[],"area":135719.308,"bbox":[98.29,194.32,377.68,359.35],"iscrowd":0,"attributes":{"occluded":false,"track_id":1,"keyframe":false},"keypoints":[125.46,242.5,1,116.94,214.92,1,98.29,236.61,1,133.47,216.16,1,103.36,262.15,1,188.03,238.41,2,150.79,289.44,2,289.48,245.46,2,194.38,360.99,2,347.08,194.32,2,143.67,362.64,1,313.62,300.21,2,277.91,346.07,2,404.69,380.74,1,272.53,449.5,2,475.97,436.82,1,304.32,553.67,2],"num_keypoints":17},{"id":65,"image_id":65,"category_id":1,"segmentation":[],"area":132673.29760000002,"bbox":[98.02,196.39,375.08,353.72],"iscrowd":0,"attributes":{"occluded":false,"track_id":1,"keyframe":false},"keypoints":[124.03,253.35,1,116.23,226.48,1,98.02,248.26,1,132.04,227.01,1,101.93,273.0,1,186.69,251.23,2,149.98,302.44,2,286.52,252.54,2,191.16,376.09,2,345.47,196.39,2,141.69,375.65,1,311.74,313.11,2,274.41,358.8,2,403.97,384.87,1,266.62,456.04,2,473.1,432.33,1,300.84,550.11,2],"num_keypoints":17},{"id":66,"image_id":66,"category_id":1,"segmentation":[],"area":129664.0128,"bbox":[97.75,198.45,372.48,348.11],"iscrowd":0,"attributes":{"occluded":false,"track_id":1,"keyframe":false},"keypoints":[122.59,264.19,1,115.51,238.04,1,97.75,259.91,1,130.61,237.86,1,100.5,283.84,1,185.34,264.05,2,149.18,315.44,2,283.56,259.62,2,187.95,391.2,2,343.85,198.45,2,139.72,388.67,1,309.86,326.02,2,270.92,371.52,2,403.25,388.99,1,260.7,462.58,2,470.23,427.85,1,297.37,546.56,2],"num_keypoints":17},{"id":67,"image_id":67,"category_id":1,"segmentation":[],"area":126683.9,"bbox":[97.48,200.51,369.88,342.5],"iscrowd":0,"attributes":{"occluded":false,"track_id":1,"keyframe":false},"keypoints":[121.16,275.04,1,114.79,249.61,1,97.48,271.57,1,129.17,248.7,1,99.06,294.69,1,184.0,276.87,2,148.37,328.44,2,280.6,266.7,2,184.73,406.31,2,342.24,200.51,2,137.74,401.69,1,307.97,338.93,2,267.42,384.25,2,402.54,393.11,1,254.78,469.13,2,467.36,423.37,1,293.89,543.01,2],"num_keypoints":17},{"id":68,"image_id":68,"category_id":1,"segmentation":[],"area":123729.28640000003,"bbox":[97.21,202.57,367.28,336.88],"iscrowd":0,"attributes":{"occluded":false,"track_id":1,"keyframe":false},"keypoints":[119.72,285.89,1,114.08,261.17,1,97.21,283.22,1,127.74,259.55,1,97.63,305.54,1,182.66,289.68,2,147.56,341.43,2,277.64,273.78,2,181.51,421.41,2,340.63,202.57,2,135.77,414.7,1,306.09,351.84,2,263.92,396.98,2,401.82,397.24,1,248.87,475.67,2,464.49,418.89,1,290.42,539.45,2],"num_keypoints":17},{"id":69,"image_id":69,"category_id":1,"segmentation":[],"area":121055.99609999999,"bbox":[96.19,204.63,365.43,331.27],"iscrowd":0,"attributes":{"occluded":false,"track_id":1,"keyframe":false},"keypoints":[118.29,296.73,1,113.36,272.73,1,96.94,294.87,1,126.3,270.39,1,96.19,316.38,1,181.31,302.5,2,146.76,354.43,2,274.69,280.86,2,178.3,436.52,2,339.01,204.63,2,133.79,427.72,1,304.21,364.74,2,260.43,409.71,2,401.1,401.36,1,242.95,482.21,2,461.62,414.41,1,286.95,535.9,2],"num_keypoints":17},{"id":70,"image_id":70,"category_id":1,"segmentation":[],"area":118536.6,"bbox":[94.76,206.69,364.0,325.65],"iscrowd":0,"attributes":{"occluded":false,"track_id":1,"keyframe":false},"keypoints":[116.86,307.58,1,112.64,284.3,1,96.68,306.52,1,124.87,281.24,1,94.76,327.23,1,179.97,315.32,2,145.95,367.43,2,271.73,287.95,2,175.08,451.63,2,337.4,206.69,2,131.81,440.73,1,302.33,377.65,2,256.93,422.44,2,400.39,405.48,1,237.04,488.76,2,458.76,409.92,1,283.47,532.34,2],"num_keypoints":17},{"id":71,"image_id":71,"category_id":1,"segmentation":[],"area":116033.27709999999,"bbox":[93.32,208.76,362.57,320.03],"iscrowd":0,"attributes":{"occluded":false,"track_id":1,"keyframe":false},"keypoints":[115.42,318.42,1,111.92,295.86,1,96.41,318.18,1,123.43,292.09,1,93.32,338.07,1,178.62,328.14,2,145.14,380.42,2,268.77,295.03,2,171.87,466.73,2,335.78,208.76,2,129.84,453.75,1,300.45,390.56,2,253.44,435.17,2,399.67,409.61,1,231.12,495.3,2,455.89,405.44,1,280.0,528.79,2],"num_keypoints":17},{"id":72,"image_id":72,"category_id":1,"segmentation":[],"area":113546.4946,"bbox":[91.89,210.82,361.13,314.42],"iscrowd":0,"attributes":{"occluded":false,"track_id":1,"keyframe":true},"keypoints":[113.99,329.27,1,111.21,307.42,1,96.14,329.83,1,122.0,302.93,1,91.89,348.92,1,177.28,340.95,2,144.34,393.42,2,265.81,302.11,2,168.65,481.84,2,334.17,210.82,2,127.86,466.76,1,298.56,403.47,2,249.94,447.89,2,398.95,413.73,2,225.2,501.84,2,453.02,400.96,1,276.52,525.24,2],"num_keypoints":17},{"id":73,"image_id":73,"category_id":1,"segmentation":[],"area":109574.95999999996,"bbox":[95.15,218.97,360.8,303.7],"iscrowd":0,"attributes":{"occluded":false,"track_id":1,"keyframe":false},"keypoints":[116.47,339.43,1,112.98,317.8,1,98.74,340.58,1,123.56,312.98,1,95.15,359.7,1,175.87,346.26,2,145.22,399.72,2,259.91,304.3,2,171.5,485.43,2,329.75,218.97,2,131.75,472.73,1,290.26,402.22,2,243.91,446.56,2,397.78,411.38,2,226.61,500.5,2,455.95,399.39,1,276.17,522.67,2],"num_keypoints":17},{"id":74,"image_id":74,"category_id":1,"segmentation":[],"area":105607.5708,"bbox":[98.42,227.12,360.46,292.98],"iscrowd":0,"attributes":{"occluded":false,"track_id":1,"keyframe":false},"keypoints":[118.95,349.59,1,114.74,328.18,1,101.34,351.33,1,125.11,323.02,1,98.42,370.49,1,174.47,351.57,2,146.11,406.02,2,254.0,306.49,2,174.34,489.01,2,325.33,227.12,2,135.65,478.69,1,281.96,400.97,2,237.87,445.23,2,396.6,409.02,2,228.02,499.16,2,458.88,397.83,1,275.82,520.1,2],"num_keypoints":17},{"id":75,"image_id":75,"category_id":1,"segmentation":[],"area":101650.2938,"bbox":[101.68,235.27,360.13,282.26],"iscrowd":0,"attributes":{"occluded":false,"track_id":1,"keyframe":false},"keypoints":[121.43,359.75,1,116.51,338.56,1,103.95,362.09,1,126.67,333.06,1,101.68,381.28,1,173.07,356.88,2,146.99,412.32,2,248.09,308.67,2,177.19,492.6,2,320.91,235.27,2,139.54,484.65,1,273.66,399.72,2,231.83,443.89,2,395.43,406.67,2,229.42,497.82,2,461.81,396.26,1,275.46,517.53,2],"num_keypoints":17},{"id":76,"image_id":76,"category_id":1,"segmentation":[],"area":97700.97450000003,"bbox":[104.95,243.42,359.79,271.55],"iscrowd":0,"attributes":{"occluded":false,"track_id":1,"keyframe":false},"keypoints":[123.91,369.91,1,118.28,348.94,1,106.55,372.84,1,128.23,343.11,1,104.95,392.06,1,171.66,362.19,2,147.88,418.62,2,242.19,310.86,2,180.03,496.19,2,316.5,243.42,2,143.43,490.62,1,265.35,398.47,2,225.8,442.56,2,394.25,404.31,2,230.83,496.48,2,464.74,394.69,1,275.11,514.97,2],"num_keypoints":17},{"id":77,"image_id":77,"category_id":1,"segmentation":[],"area":93757.95180000001,"bbox":[108.21,251.57,359.46,260.83],"iscrowd":0,"attributes":{"occluded":false,"track_id":1,"keyframe":false},"keypoints":[126.4,380.07,1,120.05,359.31,1,109.15,383.59,1,129.78,353.15,1,108.21,402.85,1,170.26,367.49,2,148.76,424.92,2,236.28,313.05,2,182.88,499.77,2,312.08,251.57,2,147.32,496.58,1,257.05,397.22,2,219.76,441.23,2,393.07,401.96,2,232.24,495.14,2,467.67,393.12,1,274.76,512.4,2],"num_keypoints":17},{"id":78,"image_id":78,"category_id":1,"segmentation":[],"area":89819.50319999999,"bbox":[111.48,259.72,359.12,250.11],"iscrowd":0,"attributes":{"occluded":false,"track_id":1,"keyframe":false},"keypoints":[128.88,390.23,1,121.82,369.69,1,111.75,394.35,1,131.34,363.19,1,111.48,413.63,1,168.86,372.8,2,149.65,431.22,2,230.37,315.24,2,185.72,503.36,2,307.66,259.72,2,151.22,502.55,1,248.75,395.97,2,213.72,439.89,2,391.9,399.61,2,233.64,493.8,2,470.6,391.55,1,274.4,509.83,2],"num_keypoints":17},{"id":79,"image_id":79,"category_id":1,"segmentation":[],"area":86430.66879999998,"bbox":[114.36,267.87,359.17,240.64],"iscrowd":0,"attributes":{"occluded":false,"track_id":1,"keyframe":false},"keypoints":[131.36,400.39,1,123.58,380.07,1,114.36,405.1,1,132.9,373.24,1,114.74,424.42,1,167.45,378.11,2,150.53,437.52,2,224.47,317.43,2,188.57,506.95,2,303.24,267.87,2,155.11,508.51,1,240.45,394.72,2,207.69,438.56,2,390.72,397.25,2,235.05,492.46,2,473.53,389.99,1,274.05,507.26,2],"num_keypoints":17},{"id":80,"image_id":80,"category_id":1,"segmentation":[],"area":85726.37000000001,"bbox":[116.96,276.02,359.5,238.46],"iscrowd":0,"attributes":{"occluded":false,"track_id":1,"keyframe":true},"keypoints":[133.84,410.55,1,125.35,390.45,1,116.96,415.85,1,134.45,383.28,1,118.0,435.2,1,166.05,383.42,2,151.42,443.82,2,218.56,319.62,2,191.41,510.54,2,298.82,276.02,2,159.0,514.48,1,232.15,393.47,2,201.65,437.23,2,389.55,394.9,2,236.46,491.12,2,476.46,388.42,1,273.7,504.7,2],"num_keypoints":17},{"id":81,"image_id":81,"category_id":1,"segmentation":[],"area":81555.46949999999,"bbox":[115.69,282.17,359.83,226.65],"iscrowd":0,"attributes":{"occluded":false,"track_id":1,"keyframe":false},"keypoints":[132.45,409.09,1,123.25,389.21,1,115.69,414.98,1,132.13,381.71,1,117.4,434.37,1,165.61,387.76,2,148.43,438.5,2,220.92,323.16,2,190.38,502.5,2,304.76,282.17,2,159.02,508.82,1,222.88,390.77,2,201.42,435.89,2,408.71,393.51,2,245.61,495.11,2,475.52,375.23,1,292.71,501.64,2],"num_keypoints":17},{"id":82,"image_id":82,"category_id":1,"segmentation":[],"area":77378.22750000001,"bbox":[114.42,288.32,360.15,214.85],"iscrowd":0,"attributes":{"occluded":false,"track_id":1,"keyframe":true},"keypoints":[131.06,407.63,1,121.14,387.96,1,114.42,414.12,1,129.82,380.13,1,116.79,433.53,1,165.18,392.1,2,145.44,433.18,2,223.27,326.7,2,189.35,494.47,2,310.69,288.32,2,159.04,503.17,1,213.61,388.07,2,201.2,434.56,2,427.87,392.12,2,254.77,499.1,2,474.57,362.04,1,311.73,498.59,2],"num_keypoints":17},{"id":83,"image_id":83,"category_id":1,"segmentation":[],"area":72361.86620000002,"bbox":[111.22,299.77,355.22,203.71],"iscrowd":0,"attributes":{"occluded":false,"track_id":1,"keyframe":false},"keypoints":[128.7,407.78,1,117.99,388.58,1,111.22,413.58,1,127.62,381.11,1,113.16,432.98,1,162.81,390.09,2,141.11,431.94,2,220.25,331.27,2,180.14,492.69,2,308.12,299.77,2,154.16,503.48,1,206.32,389.54,2,191.51,435.95,2,410.21,393.91,2,256.01,494.06,2,466.44,368.93,1,306.84,498.9,2],"num_keypoints":17},{"id":84,"image_id":84,"category_id":1,"segmentation":[],"area":67458.84820000002,"bbox":[108.02,311.21,350.29,192.58],"iscrowd":0,"attributes":{"occluded":false,"track_id":1,"keyframe":false},"keypoints":[126.34,407.93,1,114.83,389.2,1,108.02,413.05,1,125.41,382.09,1,109.54,432.42,1,160.45,388.09,2,136.77,430.7,2,217.23,335.84,2,170.92,490.9,2,305.55,311.21,2,149.28,503.79,1,199.04,391.01,2,181.83,437.35,2,392.54,395.69,2,257.25,489.02,2,458.31,375.83,1,301.96,499.21,2],"num_keypoints":17},{"id":85,"image_id":85,"category_id":1,"segmentation":[],"area":62663.75750000002,"bbox":[104.82,322.65,345.35,181.45],"iscrowd":0,"attributes":{"occluded":false,"track_id":1,"keyframe":false},"keypoints":[123.97,408.08,1,111.68,389.82,1,104.82,412.52,1,123.21,383.07,1,105.92,431.87,1,158.09,386.08,2,132.43,429.46,2,214.21,340.41,2,161.7,489.12,2,302.97,322.65,2,144.4,504.1,1,191.76,392.49,2,172.15,438.74,2,374.88,397.47,2,258.48,483.99,2,450.17,382.72,1,297.08,499.52,2],"num_keypoints":17},{"id":86,"image_id":86,"category_id":1,"segmentation":[],"area":57978.63120000002,"bbox":[101.63,334.09,340.41,170.32],"iscrowd":0,"attributes":{"occluded":false,"track_id":1,"keyframe":false},"keypoints":[121.61,408.23,1,108.53,390.44,1,101.63,411.98,1,121.01,384.05,1,102.3,431.31,1,155.72,384.08,2,128.09,428.23,2,211.19,344.98,2,152.48,487.34,2,300.4,334.09,2,139.52,504.41,1,184.48,393.96,2,162.46,440.14,2,357.22,399.25,2,259.72,478.95,2,442.04,389.62,1,292.2,499.83,2],"num_keypoints":17},{"id":87,"image_id":87,"category_id":1,"segmentation":[],"area":53403.46930000001,"bbox":[98.43,345.53,335.47,159.19],"iscrowd":0,"attributes":{"occluded":false,"track_id":1,"keyframe":false},"keypoints":[119.25,408.37,1,105.37,391.06,1,98.43,411.45,1,118.81,385.03,1,98.67,430.76,1,153.36,382.07,2,123.75,426.99,2,208.17,349.55,2,143.26,485.56,2,297.83,345.53,2,134.64,504.72,1,177.2,395.43,2,152.78,441.53,2,339.55,401.03,2,260.96,473.92,2,433.9,396.51,1,287.32,500.14,2],"num_keypoints":17},{"id":88,"image_id":88,"category_id":1,"segmentation":[],"area":49908.95519999998,"bbox":[95.05,354.12,330.72,150.91],"iscrowd":0,"attributes":{"occluded":false,"track_id":1,"keyframe":false},"keypoints":[116.89,408.52,1,102.22,391.68,1,95.23,410.92,1,116.6,386.01,1,95.05,430.2,1,151.0,380.07,2,119.41,425.75,2,205.15,354.12,2,134.04,483.78,2,295.25,356.97,2,129.76,505.03,1,169.91,396.9,2,143.1,442.93,2,321.89,402.81,2,262.2,468.88,2,425.77,403.41,1,282.44,500.45,2],"num_keypoints":17},{"id":89,"image_id":89,"category_id":1,"segmentation":[],"area":47837.22999999999,"bbox":[91.43,358.69,326.2,146.65],"iscrowd":0,"attributes":{"occluded":false,"track_id":1,"keyframe":false},"keypoints":[114.53,408.67,1,99.06,392.3,1,92.03,410.38,1,114.4,386.98,1,91.43,429.65,1,148.63,378.06,2,115.08,424.51,2,202.12,358.69,2,124.82,482.0,2,292.68,368.41,2,124.88,505.34,1,162.63,398.37,2,133.41,444.32,2,304.23,404.6,2,263.44,463.85,2,417.63,410.3,1,277.56,500.76,2],"num_keypoints":17},{"id":90,"image_id":90,"category_id":1,"segmentation":[],"area":45802.2222,"bbox":[87.81,363.27,321.69,142.38],"iscrowd":0,"attributes":{"occluded":false,"track_id":1,"keyframe":true},"keypoints":[112.17,408.82,1,95.91,392.92,1,88.84,409.85,1,112.2,387.96,1,87.81,429.09,1,146.27,376.06,2,110.74,423.27,2,199.1,363.27,2,115.6,480.21,2,290.11,379.85,2,120.0,505.65,1,155.35,399.85,2,123.73,445.71,2,286.56,406.38,2,264.68,458.81,2,409.5,417.2,2,272.68,501.07,2],"num_keypoints":17},{"id":91,"image_id":91,"category_id":1,"segmentation":[],"area":44124.763900000005,"bbox":[81.87,367.84,319.49,138.11],"iscrowd":0,"attributes":{"occluded":false,"track_id":1,"keyframe":false},"keypoints":[101.86,409.39,1,86.06,393.54,1,81.87,413.92,1,96.61,385.6,1,82.93,429.37,1,130.93,378.66,2,106.4,422.03,2,196.08,367.84,2,106.39,478.43,2,257.4,382.51,2,115.12,505.95,1,148.07,401.32,2,114.04,447.11,2,268.9,408.16,2,265.92,453.77,2,401.36,424.09,2,267.8,501.38,2],"num_keypoints":17},{"id":92,"image_id":92,"category_id":1,"segmentation":[],"area":42607.132,"bbox":[74.91,372.41,318.32,133.85],"iscrowd":0,"attributes":{"occluded":false,"track_id":1,"keyframe":true},"keypoints":[91.55,409.95,1,76.21,394.16,1,74.91,417.99,1,81.01,383.23,1,78.05,429.66,1,115.6,381.25,2,102.06,420.79,2,193.06,372.41,2,97.17,476.65,1,224.7,385.16,2,110.23,506.26,1,140.78,402.79,2,104.36,448.5,2,251.24,409.94,2,267.16,448.74,2,393.23,430.99,1,262.92,501.69,2],"num_keypoints":17},{"id":93,"image_id":93,"category_id":1,"segmentation":[],"area":43153.5404,"bbox":[70.24,373.22,322.33,133.88],"iscrowd":0,"attributes":{"occluded":false,"track_id":1,"keyframe":false},"keypoints":[87.02,411.05,1,71.55,395.31,1,70.24,419.07,1,76.39,384.4,1,73.41,430.7,1,111.76,380.98,2,97.63,421.86,2,189.02,373.22,2,92.69,477.56,1,218.61,387.01,2,105.87,507.1,1,136.68,403.91,2,102.46,449.5,2,251.38,411.72,2,264.15,449.73,2,392.57,434.06,1,259.87,502.53,2],"num_keypoints":17},{"id":94,"image_id":94,"category_id":1,"segmentation":[],"area":43695.0015,"bbox":[65.57,374.04,326.35,133.89],"iscrowd":0,"attributes":{"occluded":false,"track_id":1,"keyframe":false},"keypoints":[82.49,412.16,1,66.89,396.45,1,65.57,420.15,1,71.78,385.58,1,68.76,431.75,1,107.93,380.71,2,93.19,422.93,2,184.99,374.04,2,88.21,478.48,1,212.53,388.86,2,101.5,507.93,1,132.58,405.03,2,100.56,450.49,2,251.53,413.5,2,261.15,450.72,2,391.92,437.14,1,256.83,503.38,2],"num_keypoints":17},{"id":95,"image_id":95,"category_id":1,"segmentation":[],"area":44236.54299999999,"bbox":[60.89,374.86,330.37,133.9],"iscrowd":0,"attributes":{"occluded":false,"track_id":1,"keyframe":false},"keypoints":[77.97,413.26,1,62.23,397.59,1,60.89,421.22,1,67.16,386.75,1,64.12,432.79,1,104.09,380.44,2,88.75,424.0,2,180.95,374.86,2,83.73,479.39,1,206.44,390.7,2,97.14,508.76,1,128.48,406.15,2,98.66,451.48,2,251.68,415.28,2,258.14,451.71,2,391.26,440.21,1,253.79,504.22,2],"num_keypoints":17},{"id":96,"image_id":96,"category_id":1,"segmentation":[],"area":44776.82579999999,"bbox":[56.22,375.68,334.38,133.91],"iscrowd":0,"attributes":{"occluded":false,"track_id":1,"keyframe":false},"keypoints":[73.44,414.36,1,57.57,398.74,1,56.22,422.3,1,62.54,387.93,1,59.48,433.84,1,100.26,380.17,2,84.32,425.07,2,176.92,375.68,2,79.25,480.31,1,200.35,392.55,2,92.77,509.59,1,124.38,407.27,2,96.77,452.47,2,251.83,417.05,2,255.13,452.71,2,390.6,443.29,1,250.74,505.06,2],"num_keypoints":17},{"id":97,"image_id":97,"category_id":1,"segmentation":[],"area":45317.1888,"bbox":[51.55,376.5,338.39,133.92],"iscrowd":0,"attributes":{"occluded":false,"track_id":1,"keyframe":false},"keypoints":[68.91,415.46,1,52.91,399.88,1,51.55,423.38,1,57.92,389.1,1,54.83,434.88,1,96.42,379.89,2,79.88,426.14,2,172.88,376.5,2,74.77,481.22,1,194.27,394.4,2,88.41,510.42,1,120.28,408.39,2,94.87,453.47,2,251.97,418.83,2,252.12,453.7,2,389.94,446.36,1,247.7,505.91,2],"num_keypoints":17},{"id":98,"image_id":98,"category_id":1,"segmentation":[],"area":45858.971300000005,"bbox":[46.88,377.32,342.41,133.93],"iscrowd":0,"attributes":{"occluded":false,"track_id":1,"keyframe":false},"keypoints":[64.38,416.56,1,48.25,401.03,1,46.88,424.46,1,53.3,390.28,1,50.19,435.93,1,92.59,379.62,2,75.45,427.21,2,168.85,377.32,2,70.3,482.13,1,188.18,396.25,2,84.04,511.25,1,116.18,409.51,2,92.97,454.46,2,252.12,420.61,2,249.12,454.69,2,389.29,449.44,1,244.65,506.75,2],"num_keypoints":17},{"id":99,"image_id":99,"category_id":1,"segmentation":[],"area":46402.95900000002,"bbox":[42.21,378.13,346.42,133.95],"iscrowd":0,"attributes":{"occluded":false,"track_id":1,"keyframe":false},"keypoints":[59.86,417.66,1,43.59,402.17,1,42.21,425.53,1,48.68,391.45,1,45.54,436.97,1,88.75,379.35,2,71.01,428.28,2,164.81,378.13,2,65.82,483.05,1,182.1,398.1,2,79.68,512.08,1,112.08,410.63,2,91.07,455.45,2,252.27,422.39,2,246.11,455.68,2,388.63,452.51,1,241.61,507.6,2],"num_keypoints":17},{"id":100,"image_id":100,"category_id":1,"segmentation":[],"area":46943.60279999999,"bbox":[37.54,378.95,350.43,133.96],"iscrowd":0,"attributes":{"occluded":false,"track_id":1,"keyframe":true},"keypoints":[55.33,418.76,1,38.93,403.32,1,37.54,426.61,1,44.07,392.63,1,40.9,438.02,1,84.92,379.08,2,66.57,429.35,2,160.77,378.95,2,61.34,483.96,1,176.01,399.94,2,75.31,512.91,1,107.98,411.75,2,89.17,456.44,2,252.42,424.17,2,243.1,456.67,2,387.97,455.59,2,238.57,508.44,2],"num_keypoints":17}]}