{"licenses":[{"name":"","id":0,"url":""}],"info":{"contributor":"","date_created":"","description":"","url":"","version":"","year":""},"categories":[{"id":1,"name":"Falldown","supercategory":"","keypoints":["1","2","3","4","5","6","7","8","9","10","11","12","13","14","15","16","17"],"skeleton":[[6,12],[4,6],[12,13],[5,7],[9,11],[1,3],[15,17],[6,8],[7,13],[4,2],[5,3],[1,2],[7,9],[13,15],[7,6],[3,2],[12,14],[8,10],[16,14]]},{"id":19,"name":"Walk","supercategory":"","keypoints":["1","2","3","4","5","6","7","8","9","10","11","12","13","14","15","16","17"],"skeleton":[[6,12],[4,6],[12,13],[5,7],[9,11],[1,3],[15,17],[6,8],[7,13],[4,2],[5,3],[1,2],[7,9],[13,15],[7,6],[3,2],[12,14],[8,10],[16,14]]},{"id":37,"name":"Sit down","supercategory":"","keypoints":["1","2","3","4","5","6","7","8","9","10","11","12","13","14","15","16","17"],"skeleton":[[6,12],[4,6],[12,13],[5,7],[9,11],[1,3],[15,17],[6,8],[7,13],[4,2],[5,3],[1,2],[7,9],[13,15],[7,6],[3,2],[12,14],[8,10],[16,14]]},{"id":55,"name":"stand","supercategory":"","keypoints":["1","2","3","4","5","6","7","8","9","10","11","12","13","14","15","16","17"],"skeleton":[[6,12],[4,6],[12,13],[5,7],[9,11],[1,3],[15,17],[6,8],[7,13],[4,2],[5,3],[1,2],[7,9],[13,15],[7,6],[3,2],[12,14],[8,10],[16,14]]},{"id":73,"name":"Bend over","supercategory":"","keypoints":["1","2","3","4","5","6","7","8","9","10","11","12","13","14","15","16","17"],"skeleton":[[6,12],[4,6],[12,13],[5,7],[9,11],[1,3],[15,17],[6,8],[7,13],[4,2],[5,3],[1,2],[7,9],[13,15],[7,6],[3,2],[12,14],[8,10],[16,14]]},{"id":91,"name":"Tie shoelaces","supercategory":"","keypoints":["1","2","3","4","5","6","7","8","9","10","11","12","13","14","15","16","17"],"skeleton":[[6,12],[4,6],[12,13],[5,7],[9,11],[1,3],[15,17],[6,8],[7,13],[4,2],[5,3],[1,2],[7,9],[13,15],[7,6],[3,2],[12,14],[8,10],[16,14]]},{"id":109,"name":"Wave","supercategory":"","keypoints":["1","2","3","4","5","6","7","8","9","10","11","12","13","14","15","16","17"],"skeleton":[[6,12],[4,6],[12,13],[5,7],[9,11],[1,3],[15,17],[6,8],[7,13],[4,2],[5,3],[1,2],[7,9],[13,15],[7,6],[3,2],[12,14],[8,10],[16,14]]},{"id":127,"name":"sleep","supercategory":"","keypoints":["1","2","3","4","5","6","7","8","9","10","11","12","13","14","15","16","17"],"skeleton":[[6,12],[4,6],[12,13],[5,7],[9,11],[1,3],[15,17],[6,8],[7,13],[4,2],[5,3],[1,2],[7,9],[13,15],[7,6],[3,2],[12,14],[8,10],[16,14]]}],"images":[{"id":1,"width":640,"height":640,"file_name":"frame_000000.png","license":0,"flickr_url":"","coco_url":"","date_captured":0},{"id":2,"width":640,"height":640,"file_name":"frame_000001.png","license":0,"flickr_url":"","coco_url":"","date_captured":0},{"id":3,"width":640,"height":640,"file_name":"frame_000002.png","license":0,"flickr_url":"","coco_url":"","date_captured":0},{"id":4,"width":640,"height":640,"file_name":"frame_000003.png","license":0,"flickr_url":"","coco_url":"","date_captured":0},{"id":5,"width":640,"height":640,"file_name":"frame_000004.png","license":0,"flickr_url":"","coco_url":"","date_captured":0},{"id":6,"width":640,"height":640,"file_name":"frame_000005.png","license":0,"flickr_url":"","coco_url":"","date_captured":0},{"id":7,"width":640,"height":640,"file_name":"frame_000006.png","license":0,"flickr_url":"","coco_url":"","date_captured":0},{"id":8,"width":640,"height":640,"file_name":"frame_000007.png","license":0,"flickr_url":"","coco_url":"","date_captured":0},{"id":9,"width":640,"height":640,"file_name":"frame_000008.png","license":0,"flickr_url":"","coco_url":"","date_captured":0},{"id":10,"width":640,"height":640,"file_name":"frame_000009.png","license":0,"flickr_url":"","coco_url":"","date_captured":0},{"id":11,"width":640,"height":640,"file_name":"frame_000010.png","license":0,"flickr_url":"","coco_url":"","date_captured":0},{"id":12,"width":640,"height":640,"file_name":"frame_000011.png","license":0,"flickr_url":"","coco_url":"","date_captured":0},{"id":13,"width":640,"height":640,"file_name":"frame_000012.png","license":0,"flickr_url":"","coco_url":"","date_captured":0},{"id":14,"width":640,"height":640,"file_name":"frame_000013.png","license":0,"flickr_url":"","coco_url":"","date_captured":0},{"id":15,"width":640,"height":640,"file_name":"frame_000014.png","license":0,"flickr_url":"","coco_url":"","date_captured":0},{"id":16,"width":640,"height":640,"file_name":"frame_000015.png","license":0,"flickr_url":"","coco_url":"","date_captured":0},{"id":17,"width":640,"height":640,"file_name":"frame_000016.png","license":0,"flickr_url":"","coco_url":"","date_captured":0},{"id":18,"width":640,"height":640,"file_name":"frame_000017.png","license":0,"flickr_url":"","coco_url":"","date_captured":0},{"id":19,"width":640,"height":640,"file_name":"frame_000018.png","license":0,"flickr_url":"","coco_url":"","date_captured":0},{"id":20,"width":640,"height":640,"file_name":"frame_000019.png","license":0,"flickr_url":"","coco_url":"","date_captured":0},{"id":21,"width":640,"height":640,"file_name":"frame_000020.png","license":0,"flickr_url":"","coco_url":"","date_captured":0},{"id":22,"width":640,"height":640,"file_name":"frame_000021.png","license":0,"flickr_url":"","coco_url":"","date_captured":0},{"id":23,"width":640,"height":640,"file_name":"frame_000022.png","license":0,"flickr_url":"","coco_url":"","date_captured":0},{"id":24,"width":640,"height":640,"file_name":"frame_000023.png","license":0,"flickr_url":"","coco_url":"","date_captured":0},{"id":25,"width":640,"height":640,"file_name":"frame_000024.png","license":0,"flickr_url":"","coco_url":"","date_captured":0},{"id":26,"width":640,"height":640,"file_name":"frame_000025.png","license":0,"flickr_url":"","coco_url":"","date_captured":0},{"id":27,"width":640,"height":640,"file_name":"frame_000026.png","license":0,"flickr_url":"","coco_url":"","date_captured":0},{"id":28,"width":640,"height":640,"file_name":"frame_000027.png","license":0,"flickr_url":"","coco_url":"","date_captured":0},{"id":29,"width":640,"height":640,"file_name":"frame_000028.png","license":0,"flickr_url":"","coco_url":"","date_captured":0},{"id":30,"width":640,"height":640,"file_name":"frame_000029.png","license":0,"flickr_url":"","coco_url":"","date_captured":0},{"id":31,"width":640,"height":640,"file_name":"frame_000030.png","license":0,"flickr_url":"","coco_url":"","date_captured":0},{"id":32,"width":640,"height":640,"file_name":"frame_000031.png","license":0,"flickr_url":"","coco_url":"","date_captured":0},{"id":33,"width":640,"height":640,"file_name":"frame_000032.png","license":0,"flickr_url":"","coco_url":"","date_captured":0},{"id":34,"width":640,"height":640,"file_name":"frame_000033.png","license":0,"flickr_url":"","coco_url":"","date_captured":0},{"id":35,"width":640,"height":640,"file_name":"frame_000034.png","license":0,"flickr_url":"","coco_url":"","date_captured":0},{"id":36,"width":640,"height":640,"file_name":"frame_000035.png","license":0,"flickr_url":"","coco_url":"","date_captured":0},{"id":37,"width":640,"height":640,"file_name":"frame_000036.png","license":0,"flickr_url":"","coco_url":"","date_captured":0},{"id":38,"width":640,"height":640,"file_name":"frame_000037.png","license":0,"flickr_url":"","coco_url":"","date_captured":0},{"id":39,"width":640,"height":640,"file_name":"frame_000038.png","license":0,"flickr_url":"","coco_url":"","date_captured":0},{"id":40,"width":640,"height":640,"file_name":"frame_000039.png","license":0,"flickr_url":"","coco_url":"","date_captured":0},{"id":41,"width":640,"height":640,"file_name":"frame_000040.png","license":0,"flickr_url":"","coco_url":"","date_captured":0},{"id":42,"width":640,"height":640,"file_name":"frame_000041.png","license":0,"flickr_url":"","coco_url":"","date_captured":0},{"id":43,"width":640,"height":640,"file_name":"frame_000042.png","license":0,"flickr_url":"","coco_url":"","date_captured":0},{"id":44,"width":640,"height":640,"file_name":"frame_000043.png","license":0,"flickr_url":"","coco_url":"","date_captured":0},{"id":45,"width":640,"height":640,"file_name":"frame_000044.png","license":0,"flickr_url":"","coco_url":"","date_captured":0},{"id":46,"width":640,"height":640,"file_name":"frame_000045.png","license":0,"flickr_url":"","coco_url":"","date_captured":0},{"id":47,"width":640,"height":640,"file_name":"frame_000046.png","license":0,"flickr_url":"","coco_url":"","date_captured":0},{"id":48,"width":640,"height":640,"file_name":"frame_000047.png","license":0,"flickr_url":"","coco_url":"","date_captured":0},{"id":49,"width":640,"height":640,"file_name":"frame_000048.png","license":0,"flickr_url":"","coco_url":"","date_captured":0},{"id":50,"width":640,"height":640,"file_name":"frame_000049.png","license":0,"flickr_url":"","coco_url":"","date_captured":0},{"id":51,"width":640,"height":640,"file_name":"frame_000050.png","license":0,"flickr_url":"","coco_url":"","date_captured":0},{"id":52,"width":640,"height":640,"file_name":"frame_000051.png","license":0,"flickr_url":"","coco_url":"","date_captured":0},{"id":53,"width":640,"height":640,"file_name":"frame_000052.png","license":0,"flickr_url":"","coco_url":"","date_captured":0},{"id":54,"width":640,"height":640,"file_name":"frame_000053.png","license":0,"flickr_url":"","coco_url":"","date_captured":0},{"id":55,"width":640,"height":640,"file_name":"frame_000054.png","license":0,"flickr_url":"","coco_url":"","date_captured":0},{"id":56,"width":640,"height":640,"file_name":"frame_000055.png","license":0,"flickr_url":"","coco_url":"","date_captured":0},{"id":57,"width":640,"height":640,"file_name":"frame_000056.png","license":0,"flickr_url":"","coco_url":"","date_captured":0},{"id":58,"width":640,"height":640,"file_name":"frame_000057.png","license":0,"flickr_url":"","coco_url":"","date_captured":0},{"id":59,"width":640,"height":640,"file_name":"frame_000058.png","license":0,"flickr_url":"","coco_url":"","date_captured":0},{"id":60,"width":640,"height":640,"file_name":"frame_000059.png","license":0,"flickr_url":"","coco_url":"","date_captured":0},{"id":61,"width":640,"height":640,"file_name":"frame_000060.png","license":0,"flickr_url":"","coco_url":"","date_captured":0},{"id":62,"width":640,"height":640,"file_name":"frame_000061.png","license":0,"flickr_url":"","coco_url":"","date_captured":0},{"id":63,"width":640,"height":640,"file_name":"frame_000062.png","license":0,"flickr_url":"","coco_url":"","date_captured":0},{"id":64,"width":640,"height":640,"file_name":"frame_000063.png","license":0,"flickr_url":"","coco_url":"","date_captured":0},{"id":65,"width":640,"height":640,"file_name":"frame_000064.png","license":0,"flickr_url":"","coco_url":"","date_captured":0},{"id":66,"width":640,"height":640,"file_name":"frame_000065.png","license":0,"flickr_url":"","coco_url":"","date_captured":0},{"id":67,"width":640,"height":640,"file_name":"frame_000066.png","license":0,"flickr_url":"","coco_url":"","date_captured":0},{"id":68,"width":640,"height":640,"file_name":"frame_000067.png","license":0,"flickr_url":"","coco_url":"","date_captured":0},{"id":69,"width":640,"height":640,"file_name":"frame_000068.png","license":0,"flickr_url":"","coco_url":"","date_captured":0},{"id":70,"width":640,"height":640,"file_name":"frame_000069.png","license":0,"flickr_url":"","coco_url":"","date_captured":0},{"id":71,"width":640,"height":640,"file_name":"frame_000070.png","license":0,"flickr_url":"","coco_url":"","date_captured":0},{"id":72,"width":640,"height":640,"file_name":"frame_000071.png","license":0,"flickr_url":"","coco_url":"","date_captured":0},{"id":73,"width":640,"height":640,"file_name":"frame_000072.png","license":0,"flickr_url":"","coco_url":"","date_captured":0},{"id":74,"width":640,"height":640,"file_name":"frame_000073.png","license":0,"flickr_url":"","coco_url":"","date_captured":0},{"id":75,"width":640,"height":640,"file_name":"frame_000074.png","license":0,"flickr_url":"","coco_url":"","date_captured":0},{"id":76,"width":640,"height":640,"file_name":"frame_000075.png","license":0,"flickr_url":"","coco_url":"","date_captured":0},{"id":77,"width":640,"height":640,"file_name":"frame_000076.png","license":0,"flickr_url":"","coco_url":"","date_captured":0},{"id":78,"width":640,"height":640,"file_name":"frame_000077.png","license":0,"flickr_url":"","coco_url":"","date_captured":0},{"id":79,"width":640,"height":640,"file_name":"frame_000078.png","license":0,"flickr_url":"","coco_url":"","date_captured":0},{"id":80,"width":640,"height":640,"file_name":"frame_000079.png","license":0,"flickr_url":"","coco_url":"","date_captured":0},{"id":81,"width":640,"height":640,"file_name":"frame_000080.png","license":0,"flickr_url":"","coco_url":"","date_captured":0},{"id":82,"width":640,"height":640,"file_name":"frame_000081.png","license":0,"flickr_url":"","coco_url":"","date_captured":0},{"id":83,"width":640,"height":640,"file_name":"frame_000082.png","license":0,"flickr_url":"","coco_url":"","date_captured":0},{"id":84,"width":640,"height":640,"file_name":"frame_000083.png","license":0,"flickr_url":"","coco_url":"","date_captured":0},{"id":85,"width":640,"height":640,"file_name":"frame_000084.png","license":0,"flickr_url":"","coco_url":"","date_captured":0},{"id":86,"width":640,"height":640,"file_name":"frame_000085.png","license":0,"flickr_url":"","coco_url":"","date_captured":0},{"id":87,"width":640,"height":640,"file_name":"frame_000086.png","license":0,"flickr_url":"","coco_url":"","date_captured":0},{"id":88,"width":640,"height":640,"file_name":"frame_000087.png","license":0,"flickr_url":"","coco_url":"","date_captured":0},{"id":89,"width":640,"height":640,"file_name":"frame_000088.png","license":0,"flickr_url":"","coco_url":"","date_captured":0},{"id":90,"width":640,"height":640,"file_name":"frame_000089.png","license":0,"flickr_url":"","coco_url":"","date_captured":0},{"id":91,"width":640,"height":640,"file_name":"frame_000090.png","license":0,"flickr_url":"","coco_url":"","date_captured":0},{"id":92,"width":640,"height":640,"file_name":"frame_000091.png","license":0,"flickr_url":"","coco_url":"","date_captured":0},{"id":93,"width":640,"height":640,"file_name":"frame_000092.png","license":0,"flickr_url":"","coco_url":"","date_captured":0},{"id":94,"width":640,"height":640,"file_name":"frame_000093.png","license":0,"flickr_url":"","coco_url":"","date_captured":0},{"id":95,"width":640,"height":640,"file_name":"frame_000094.png","license":0,"flickr_url":"","coco_url":"","date_captured":0},{"id":96,"width":640,"height":640,"file_name":"frame_000095.png","license":0,"flickr_url":"","coco_url":"","date_captured":0},{"id":97,"width":640,"height":640,"file_name":"frame_000096.png","license":0,"flickr_url":"","coco_url":"","date_captured":0}],"annotations":[{"id":1,"image_id":1,"category_id":19,"segmentation":[],"area":62082.16760000001,"bbox":[164.62,307.43,183.86,337.66],"iscrowd":0,"attributes":{"occluded":false,"keyframe":false},"keypoints":[229.55,319.31,1,241.92,309.96,1,213.07,307.43,1,246.37,320.0,1,207.72,320.96,1,280.02,365.82,2,177.71,380.21,2,316.57,442.09,2,164.62,450.24,2,348.48,485.05,2,192.83,450.68,1,293.8,496.33,2,231.81,520.45,2,301.81,549.63,2,248.09,579.49,2,310.37,621.23,2,262.87,645.09,1],"num_keypoints":17},{"id":2,"image_id":2,"category_id":19,"segmentation":[],"area":60617.79839999999,"bbox":[171.52,298.43,178.12,340.32],"iscrowd":0,"attributes":{"occluded":false,"keyframe":false},"keypoints":[233.82,314.42,1,248.25,300.96,1,219.39,298.43,1,248.58,312.03,1,219.17,314.01,1,286.35,356.82,2,184.03,371.2,2,322.89,433.09,2,171.52,437.8,2,349.64,479.49,2,189.98,443.97,1,300.12,487.33,2,238.13,511.45,2,305.47,551.28,2,254.42,570.49,2,306.92,614.89,2,260.32,638.75,1],"num_keypoints":17},{"id":3,"image_id":3,"category_id":19,"segmentation":[],"area":61825.93439999999,"bbox":[171.52,298.43,181.67,340.32],"iscrowd":0,"attributes":{"occluded":false,"keyframe":false},"keypoints":[237.37,309.1,1,249.13,299.19,1,222.95,298.43,1,253.91,311.14,1,221.84,314.01,1,286.35,356.82,2,192.02,369.43,2,325.55,431.31,2,171.52,437.8,2,353.19,476.83,2,189.98,443.97,1,300.12,490.88,2,238.13,511.45,2,305.47,551.28,2,254.42,570.49,2,307.81,618.45,2,260.32,638.75,1],"num_keypoints":17},{"id":4,"image_id":4,"category_id":19,"segmentation":[],"area":61825.93439999999,"bbox":[171.52,298.43,181.67,340.32],"iscrowd":0,"attributes":{"occluded":false,"keyframe":false},"keypoints":[237.37,309.1,1,249.13,299.19,1,222.95,298.43,1,253.91,311.14,1,221.84,314.01,1,286.35,356.82,2,199.13,371.2,2,325.55,431.31,2,171.52,437.8,2,353.19,476.83,2,189.98,443.97,1,300.12,490.88,2,238.13,511.45,2,305.47,551.28,2,254.42,570.49,2,310.47,614.89,2,260.32,638.75,1],"num_keypoints":17},{"id":5,"image_id":5,"category_id":19,"segmentation":[],"area":60314.91359999999,"bbox":[178.72,289.79,177.23,340.32],"iscrowd":0,"attributes":{"occluded":false,"keyframe":false},"keypoints":[240.13,300.46,1,257.22,290.55,1,228.37,289.79,1,256.67,302.5,1,224.6,305.38,1,289.11,348.18,2,201.89,362.57,2,328.31,422.67,2,178.72,426.5,2,355.95,468.19,2,193.63,435.33,1,302.88,482.24,2,240.89,502.81,2,308.23,542.64,2,257.18,561.85,2,314.12,616.91,2,263.08,630.11,1],"num_keypoints":17},{"id":6,"image_id":6,"category_id":19,"segmentation":[],"area":60314.91359999999,"bbox":[182.72,283.58,177.23,340.32],"iscrowd":0,"attributes":{"occluded":false,"keyframe":false},"keypoints":[244.13,294.24,1,261.22,284.33,1,232.37,283.58,1,260.66,296.28,1,228.6,299.16,1,293.1,341.96,2,205.88,356.35,2,332.31,416.46,2,182.72,420.28,2,359.95,461.97,2,197.63,429.12,1,306.88,476.02,2,244.89,496.59,2,312.22,536.43,2,261.18,555.64,2,318.12,610.69,2,267.07,623.9,1],"num_keypoints":17},{"id":7,"image_id":7,"category_id":19,"segmentation":[],"area":58902.16919999999,"bbox":[187.15,275.59,177.24,332.33],"iscrowd":0,"attributes":{"occluded":false,"keyframe":false},"keypoints":[248.57,286.25,1,265.66,276.34,1,236.81,275.59,1,265.1,288.29,1,233.03,291.17,1,297.54,333.97,2,210.32,348.36,2,336.75,408.47,2,187.15,412.29,2,364.39,453.98,2,202.07,421.13,1,311.32,468.03,2,249.33,488.6,2,316.66,528.44,2,268.28,546.76,2,322.56,602.7,2,278.62,607.92,1],"num_keypoints":17},{"id":8,"image_id":8,"category_id":19,"segmentation":[],"area":58898.845900000015,"bbox":[189.82,275.14,177.23,332.33],"iscrowd":0,"attributes":{"occluded":false,"keyframe":false},"keypoints":[251.23,285.81,1,268.32,275.9,1,239.47,275.14,1,267.77,287.85,1,235.7,290.73,1,300.21,333.53,2,212.99,347.92,2,339.41,408.02,2,189.82,411.85,2,367.05,453.54,2,204.73,420.69,1,313.98,467.59,2,251.99,488.16,2,319.33,527.99,2,270.94,546.31,2,325.22,602.26,2,281.28,607.47,1],"num_keypoints":17},{"id":9,"image_id":9,"category_id":19,"segmentation":[],"area":63166.5443,"bbox":[194.26,265.38,177.23,356.41],"iscrowd":0,"attributes":{"occluded":false,"keyframe":false},"keypoints":[255.67,276.04,1,272.76,266.13,1,243.91,265.38,1,272.21,278.08,1,240.14,280.96,1,304.65,323.76,2,217.43,338.15,2,343.85,398.26,2,194.26,402.08,2,371.49,443.77,2,209.17,410.92,1,318.42,457.82,2,256.43,478.39,2,320.21,543.98,2,275.38,536.55,2,327.0,621.79,2,285.72,597.7,1],"num_keypoints":17},{"id":10,"image_id":10,"category_id":19,"segmentation":[],"area":63168.3166,"bbox":[195.15,269.31,177.23,356.42],"iscrowd":0,"attributes":{"occluded":false,"keyframe":false},"keypoints":[256.56,279.98,1,273.65,270.07,1,244.8,269.31,1,273.09,282.02,1,241.03,284.9,1,305.54,327.7,2,218.31,342.09,2,344.74,402.2,2,195.15,406.02,2,372.38,447.71,2,210.06,414.86,1,319.31,461.76,2,257.32,482.33,2,321.1,547.91,2,276.27,540.49,2,327.89,625.73,2,286.61,601.64,1],"num_keypoints":17},{"id":11,"image_id":11,"category_id":19,"segmentation":[],"area":63171.88080000003,"bbox":[196.92,266.65,177.24,356.42],"iscrowd":0,"attributes":{"occluded":false,"keyframe":false},"keypoints":[258.33,277.31,1,275.43,267.4,1,246.57,266.65,1,274.87,279.36,1,242.8,282.23,1,307.31,325.04,2,220.09,339.42,2,346.52,399.53,2,196.92,403.35,2,374.16,445.04,2,211.83,412.19,1,321.09,459.1,2,259.1,479.66,2,322.88,545.25,2,278.04,537.82,2,329.66,623.07,2,288.38,598.98,1],"num_keypoints":17},{"id":12,"image_id":12,"category_id":19,"segmentation":[],"area":63171.8808,"bbox":[200.47,262.21,177.24,356.42],"iscrowd":0,"attributes":{"occluded":false,"keyframe":false},"keypoints":[261.88,272.88,1,278.98,262.97,1,250.13,262.21,1,278.42,274.92,1,246.35,277.79,1,310.86,320.6,2,223.64,334.98,2,350.07,395.09,2,200.47,398.91,2,377.71,440.6,2,215.38,407.75,1,324.64,454.66,2,262.65,475.23,2,326.43,540.81,2,281.6,533.38,2,333.21,618.63,2,291.94,594.54,1],"num_keypoints":17},{"id":13,"image_id":13,"category_id":19,"segmentation":[],"area":61908.211299999995,"bbox":[203.14,263.1,177.23,349.31],"iscrowd":0,"attributes":{"occluded":false,"keyframe":false},"keypoints":[264.55,274.65,1,278.09,264.74,1,256.34,263.1,1,281.08,273.14,1,250.79,273.35,1,311.75,319.71,2,226.3,333.21,2,352.73,388.88,2,203.14,392.7,2,380.37,434.39,2,218.05,401.54,1,322.86,456.43,2,265.31,469.01,2,329.09,534.6,2,284.26,527.17,2,335.88,612.41,2,294.6,588.32,1],"num_keypoints":17},{"id":14,"image_id":14,"category_id":19,"segmentation":[],"area":61121.31010000002,"bbox":[203.14,262.21,177.23,344.87],"iscrowd":0,"attributes":{"occluded":false,"keyframe":false},"keypoints":[264.55,273.76,1,278.09,263.85,1,256.34,262.21,1,281.08,272.25,1,250.79,272.47,1,311.75,318.82,2,226.3,332.32,2,352.73,387.99,2,203.14,391.81,2,380.37,433.5,2,218.05,400.65,1,325.53,459.98,2,272.41,471.67,2,329.09,533.71,2,294.03,532.5,1,341.21,607.08,2,307.92,586.55,1],"num_keypoints":17},{"id":15,"image_id":15,"category_id":19,"segmentation":[],"area":61911.704399999995,"bbox":[204.91,260.44,177.24,349.31],"iscrowd":0,"attributes":{"occluded":false,"keyframe":false},"keypoints":[266.32,271.99,1,277.2,262.08,1,258.12,260.44,1,282.86,270.48,1,252.57,270.69,1,313.53,317.05,2,228.08,330.54,2,354.51,386.21,2,204.91,390.03,2,382.15,431.72,2,219.82,398.87,1,329.97,462.65,2,282.18,474.34,2,335.31,531.93,2,295.8,528.05,1,347.42,609.75,2,307.92,589.21,1],"num_keypoints":17},{"id":16,"image_id":16,"category_id":19,"segmentation":[],"area":60828.88059999999,"bbox":[207.58,262.09,177.23,343.22],"iscrowd":0,"attributes":{"occluded":false,"keyframe":false},"keypoints":[268.99,272.87,1,278.69,262.2,1,256.94,262.09,1,285.52,271.36,1,251.39,275.42,1,316.19,317.93,2,230.74,331.43,2,357.17,387.1,2,207.58,390.92,2,384.81,432.61,2,222.49,399.76,1,332.63,454.66,2,279.52,469.01,2,341.97,531.28,2,298.46,531.61,1,348.31,605.31,1,309.69,582.11,1],"num_keypoints":17},{"id":17,"image_id":17,"category_id":19,"segmentation":[],"area":57153.598,"bbox":[215.57,254.22,166.58,343.1],"iscrowd":0,"attributes":{"occluded":false,"keyframe":false},"keypoints":[266.32,265.77,1,279.87,255.86,1,258.12,254.22,1,282.86,264.26,1,252.57,264.48,1,313.53,310.83,2,232.52,325.22,2,354.51,380.0,2,215.57,382.93,2,382.15,425.51,2,229.59,394.43,1,330.85,446.67,2,283.96,461.02,2,337.97,525.72,2,296.69,519.18,1,349.2,597.32,1,313.25,575.89,1],"num_keypoints":17},{"id":18,"image_id":18,"category_id":19,"segmentation":[],"area":58174.66679999999,"bbox":[215.99,255.99,173.49,335.32],"iscrowd":0,"attributes":{"occluded":false,"keyframe":false},"keypoints":[263.68,268.2,1,272.62,255.99,1,254.7,258.19,1,279.45,265.16,1,249.16,269.98,1,313.95,304.82,2,232.94,319.21,2,360.3,373.22,2,215.99,376.92,2,389.48,419.5,2,230.01,388.42,1,331.28,440.66,2,284.38,455.01,2,343.0,514.34,2,300.95,526.21,1,350.39,591.31,1,308.3,580.63,1],"num_keypoints":17},{"id":19,"image_id":19,"category_id":19,"segmentation":[],"area":56818.49279999999,"bbox":[215.61,248.26,175.02,324.64],"iscrowd":0,"attributes":{"occluded":false,"keyframe":false},"keypoints":[263.29,260.48,1,272.23,248.26,1,254.32,250.46,1,279.06,257.43,1,248.77,262.25,1,313.57,297.1,2,232.56,311.48,2,359.92,365.49,2,215.61,369.19,2,390.63,409.47,2,230.4,382.23,1,333.2,434.46,2,283.23,447.28,2,346.45,502.0,2,300.57,518.49,1,350.0,571.3,1,307.91,572.9,1],"num_keypoints":17},{"id":20,"image_id":20,"category_id":19,"segmentation":[],"area":56821.73919999999,"bbox":[216.37,248.26,175.03,324.64],"iscrowd":0,"attributes":{"occluded":false,"keyframe":false},"keypoints":[264.06,260.48,1,273.0,248.26,1,255.09,250.46,1,279.83,257.43,1,249.54,262.25,1,314.33,297.1,2,233.33,311.48,2,362.22,360.89,2,216.37,369.19,2,391.4,401.8,2,231.17,382.23,1,333.96,434.46,2,284.0,447.28,1,345.69,488.96,2,301.33,518.49,1,350.77,555.19,1,308.68,572.9,1],"num_keypoints":17},{"id":21,"image_id":21,"category_id":19,"segmentation":[],"area":56816.74259999999,"bbox":[218.68,242.13,175.02,324.63],"iscrowd":0,"attributes":{"occluded":false,"keyframe":false},"keypoints":[266.36,254.34,1,275.3,242.13,1,257.39,244.32,1,282.13,251.29,1,251.84,256.11,1,316.64,290.96,2,235.63,305.34,2,364.52,354.75,2,218.68,363.06,2,393.7,395.66,2,233.47,376.09,1,336.26,428.33,2,286.3,441.14,1,351.83,478.98,2,303.64,512.35,1,350.77,545.21,1,310.98,566.76,1],"num_keypoints":17},{"id":22,"image_id":22,"category_id":19,"segmentation":[],"area":56816.742600000005,"bbox":[220.21,242.13,175.02,324.63],"iscrowd":0,"attributes":{"occluded":false,"keyframe":false},"keypoints":[267.9,254.34,1,276.84,242.13,1,258.92,244.32,1,283.67,251.29,1,253.38,256.11,1,318.17,290.96,2,237.16,305.34,2,366.06,354.75,2,220.21,363.06,2,395.23,395.66,2,235.0,376.09,1,337.8,428.33,2,287.83,441.14,1,350.29,475.15,2,305.17,512.35,1,353.07,543.68,1,312.52,566.76,1],"num_keypoints":17},{"id":23,"image_id":23,"category_id":19,"segmentation":[],"area":56819.98889999999,"bbox":[221.74,238.29,175.03,324.63],"iscrowd":0,"attributes":{"occluded":false,"keyframe":false},"keypoints":[269.43,250.5,1,278.37,238.29,1,260.46,240.48,1,285.2,247.46,1,254.91,252.27,1,319.7,287.12,2,238.7,301.5,2,367.59,350.91,2,221.74,359.22,2,396.77,391.82,2,236.54,372.25,1,339.33,424.49,2,289.37,437.31,1,348.76,474.38,2,306.7,508.51,1,353.07,546.75,1,314.05,562.92,1],"num_keypoints":17},{"id":24,"image_id":24,"category_id":19,"segmentation":[],"area":56818.49279999999,"bbox":[224.82,230.61,175.02,324.64],"iscrowd":0,"attributes":{"occluded":false,"keyframe":false},"keypoints":[272.5,242.83,1,281.44,230.61,1,263.53,232.81,1,288.27,239.78,1,257.98,244.6,1,322.78,279.45,2,241.77,293.83,2,370.66,343.24,2,224.82,351.55,2,399.84,384.15,2,239.61,364.58,1,342.4,416.81,2,292.44,429.63,1,354.13,470.54,2,309.78,500.84,1,359.98,549.82,1,317.12,555.25,1],"num_keypoints":17},{"id":25,"image_id":25,"category_id":19,"segmentation":[],"area":56414.19659999999,"bbox":[224.05,229.82,175.02,322.33],"iscrowd":0,"attributes":{"occluded":false,"keyframe":false},"keypoints":[279.41,239.73,1,283.74,229.82,1,265.83,232.78,1,291.34,235.91,1,259.51,243.04,1,322.01,276.35,2,244.84,292.26,2,369.89,340.14,2,224.05,348.45,2,399.07,381.05,2,238.84,361.48,1,347.78,406.04,2,291.67,426.53,1,357.97,466.67,2,309.01,497.74,1,359.21,546.72,1,316.36,552.15,1],"num_keypoints":17},{"id":26,"image_id":26,"category_id":19,"segmentation":[],"area":56414.19659999999,"bbox":[226.35,224.83,175.02,322.33],"iscrowd":0,"attributes":{"occluded":false,"keyframe":false},"keypoints":[278.64,236.27,1,286.04,224.83,1,268.13,227.79,1,293.64,230.93,1,261.82,238.05,1,324.31,271.36,2,247.14,287.28,2,372.2,335.15,2,226.35,343.46,2,401.37,376.06,2,241.14,356.49,1,350.08,401.05,2,293.97,421.54,1,360.27,461.69,2,311.31,492.75,1,361.51,541.73,1,318.66,547.16,1],"num_keypoints":17},{"id":27,"image_id":27,"category_id":19,"segmentation":[],"area":54684.981000000014,"bbox":[233.26,223.29,169.65,322.34],"iscrowd":0,"attributes":{"occluded":false,"keyframe":false},"keypoints":[285.55,234.74,1,292.95,223.29,1,275.04,226.26,1,298.25,231.69,1,268.72,236.51,1,331.22,269.82,2,254.05,285.74,2,379.1,337.45,2,233.26,341.92,2,402.91,379.13,2,248.05,354.96,1,356.99,399.52,2,300.88,420.01,1,358.73,457.08,2,318.22,491.21,1,368.42,540.19,1,325.57,545.63,1],"num_keypoints":17},{"id":28,"image_id":28,"category_id":19,"segmentation":[],"area":54684.98100000001,"bbox":[234.41,223.29,169.65,322.34],"iscrowd":0,"attributes":{"occluded":false,"keyframe":false},"keypoints":[286.7,234.74,1,294.1,223.29,1,276.19,226.26,1,299.4,231.69,1,269.87,236.51,1,332.37,269.82,2,255.2,285.74,2,380.25,337.45,2,234.41,341.92,2,404.06,379.13,2,249.2,354.96,1,352.0,404.89,2,302.03,420.01,1,360.65,458.62,2,319.37,491.21,1,367.27,532.52,1,326.72,545.63,1],"num_keypoints":17},{"id":29,"image_id":29,"category_id":19,"segmentation":[],"area":52952.37240000001,"bbox":[242.08,220.99,164.28,322.33],"iscrowd":0,"attributes":{"occluded":false,"keyframe":false},"keypoints":[289.0,232.44,1,296.4,220.99,1,278.49,223.96,1,301.7,229.39,1,272.18,234.21,1,334.67,267.52,2,257.5,283.44,2,382.55,335.15,2,242.08,338.85,2,406.36,376.83,2,259.17,351.89,1,354.3,402.59,2,304.33,417.71,1,362.95,456.32,2,321.67,488.91,1,369.57,530.22,1,329.02,543.32,1],"num_keypoints":17},{"id":30,"image_id":30,"category_id":19,"segmentation":[],"area":52954.015200000016,"bbox":[247.07,214.85,164.28,322.34],"iscrowd":0,"attributes":{"occluded":false,"keyframe":false},"keypoints":[293.99,226.3,1,301.39,214.85,1,283.48,217.82,1,306.69,223.25,1,277.16,228.07,1,341.19,265.22,2,264.02,281.14,2,387.54,329.01,2,247.07,332.71,2,411.35,370.69,2,264.16,345.75,1,359.29,396.45,2,309.32,411.57,1,365.64,452.48,2,326.66,482.77,1,372.26,522.54,1,334.01,537.19,1],"num_keypoints":17},{"id":31,"image_id":31,"category_id":19,"segmentation":[],"area":53203.72080000001,"bbox":[250.14,214.09,164.28,323.86],"iscrowd":0,"attributes":{"occluded":false,"keyframe":false},"keypoints":[306.27,228.6,1,313.67,214.09,1,291.92,218.58,1,317.43,224.02,1,288.68,229.61,1,348.27,265.41,2,272.25,280.76,2,390.61,329.78,2,250.14,333.48,2,414.42,371.45,2,267.23,346.52,1,360.05,397.98,2,312.39,412.34,1,367.94,453.25,2,329.73,483.54,1,375.33,523.31,1,337.08,537.95,1],"num_keypoints":17},{"id":32,"image_id":32,"category_id":19,"segmentation":[],"area":52455.604199999994,"bbox":[257.43,210.0,161.97,323.86],"iscrowd":0,"attributes":{"occluded":false,"keyframe":false},"keypoints":[311.26,224.51,1,318.66,210.0,1,296.91,214.5,1,322.42,219.93,1,293.66,225.52,1,353.26,261.32,2,277.24,276.67,2,389.46,328.76,2,257.43,326.32,2,419.4,367.36,2,272.22,342.43,1,361.97,394.66,2,317.38,408.25,1,372.93,449.16,2,334.71,479.45,1,380.31,519.22,1,342.06,533.86,1],"num_keypoints":17},{"id":33,"image_id":33,"category_id":19,"segmentation":[],"area":48666.6174,"bbox":[260.11,209.23,157.38,309.23],"iscrowd":0,"attributes":{"occluded":false,"keyframe":false},"keypoints":[317.78,223.74,1,325.18,209.23,1,303.43,213.73,1,328.94,219.16,1,300.19,224.75,1,359.79,259.02,2,286.83,269.76,2,389.85,324.15,2,260.11,317.12,2,417.49,368.13,2,270.3,338.59,1,362.36,395.43,2,312.39,397.5,1,372.55,441.48,2,314.38,452.59,1,386.84,518.46,1,326.33,506.24,1],"num_keypoints":17},{"id":34,"image_id":34,"category_id":19,"segmentation":[],"area":48666.6174,"bbox":[260.11,209.23,157.38,309.23],"iscrowd":0,"attributes":{"occluded":false,"keyframe":false},"keypoints":[317.78,223.74,1,325.18,209.23,1,303.43,213.73,1,328.94,219.16,1,300.19,224.75,1,359.79,259.02,2,286.83,269.76,2,389.85,324.15,2,260.11,317.12,2,417.49,368.13,2,270.3,338.59,1,362.36,395.43,2,312.39,397.5,1,372.55,441.48,2,314.38,452.59,1,386.84,518.46,1,326.33,506.24,1],"num_keypoints":17},{"id":35,"image_id":35,"category_id":19,"segmentation":[],"area":49017.3786,"bbox":[260.11,210.0,158.91,308.46],"iscrowd":0,"attributes":{"occluded":false,"keyframe":false},"keypoints":[325.45,223.74,1,330.55,210.0,1,311.11,212.19,1,335.08,218.4,1,307.86,224.75,1,367.46,261.32,2,286.83,269.76,2,392.92,321.85,2,260.11,317.12,2,419.02,363.53,2,270.3,338.59,1,362.36,395.43,1,312.39,397.5,1,372.55,441.48,2,314.38,452.59,1,386.84,518.46,1,326.33,506.24,1],"num_keypoints":17},{"id":36,"image_id":36,"category_id":19,"segmentation":[],"area":49964.3508,"bbox":[261.65,211.56,161.98,308.46],"iscrowd":0,"attributes":{"occluded":false,"keyframe":false},"keypoints":[326.99,225.31,1,332.09,211.56,1,312.64,213.76,1,336.62,219.96,1,309.4,226.32,1,368.99,262.89,2,288.37,271.33,2,395.98,322.65,2,261.65,318.68,2,423.63,362.02,2,271.84,340.16,1,363.89,396.99,1,313.92,399.07,1,374.08,443.05,1,315.91,454.16,1,388.37,520.02,1,327.87,507.8,1],"num_keypoints":17},{"id":37,"image_id":37,"category_id":19,"segmentation":[],"area":47598.46259999999,"bbox":[266.25,213.1,154.31,308.46],"iscrowd":0,"attributes":{"occluded":false,"keyframe":false},"keypoints":[331.59,226.84,1,336.69,213.1,1,317.25,215.29,1,341.22,221.5,1,314.0,227.85,1,373.6,264.42,2,292.97,272.86,2,400.59,324.18,2,266.25,320.22,2,420.56,355.12,2,276.44,341.69,1,368.5,398.53,1,318.53,408.28,2,378.69,444.58,1,320.52,455.69,1,392.98,521.56,1,332.47,509.34,1],"num_keypoints":17},{"id":38,"image_id":38,"category_id":19,"segmentation":[],"area":45938.94780000001,"bbox":[269.32,221.54,148.93,308.46],"iscrowd":0,"attributes":{"occluded":false,"keyframe":false},"keypoints":[330.83,235.29,1,335.93,221.54,1,316.48,223.74,1,340.46,229.94,1,313.23,236.29,1,372.83,272.87,2,292.2,281.3,2,405.19,325.72,2,269.32,321.75,2,418.25,345.91,2,284.11,324.04,1,367.73,402.37,1,316.99,409.81,2,377.92,453.03,1,319.75,464.13,1,392.21,530.0,1,331.7,517.78,1],"num_keypoints":17},{"id":39,"image_id":39,"category_id":19,"segmentation":[],"area":44796.65470000001,"bbox":[268.94,223.07,148.93,300.79],"iscrowd":0,"attributes":{"occluded":false,"keyframe":false},"keypoints":[328.91,236.82,1,334.77,223.07,1,316.09,227.57,1,340.07,234.54,1,313.62,237.06,1,372.45,266.73,2,291.82,275.16,2,404.81,319.58,2,268.94,315.61,2,417.87,339.77,2,283.73,317.9,1,367.34,396.23,1,316.61,403.67,2,377.53,446.89,1,323.2,454.16,1,391.83,523.86,1,331.32,511.64,1],"num_keypoints":17},{"id":40,"image_id":40,"category_id":19,"segmentation":[],"area":44796.65470000001,"bbox":[268.94,223.07,148.93,300.79],"iscrowd":0,"attributes":{"occluded":false,"keyframe":false},"keypoints":[328.91,236.82,1,334.77,223.07,1,316.09,227.57,1,340.07,234.54,1,313.62,237.06,1,372.45,266.73,2,291.82,275.16,2,404.81,319.58,2,268.94,315.61,2,417.87,339.77,2,283.73,317.9,1,367.34,396.23,1,316.61,403.67,2,377.53,446.89,1,323.2,454.16,1,391.83,523.86,1,331.32,511.64,1],"num_keypoints":17},{"id":41,"image_id":41,"category_id":19,"segmentation":[],"area":42817.7499,"bbox":[268.94,227.68,151.23,283.13],"iscrowd":0,"attributes":{"occluded":false,"keyframe":false},"keypoints":[328.91,241.43,1,334.78,227.68,1,316.09,232.18,1,340.07,239.15,1,313.62,241.66,1,372.45,271.33,2,291.82,279.77,2,397.14,312.67,2,268.94,320.22,2,420.17,331.33,2,283.73,322.51,1,374.25,382.41,1,321.98,392.93,2,383.67,446.89,1,327.81,444.18,1,388.76,510.81,1,339.76,500.13,1],"num_keypoints":17},{"id":42,"image_id":42,"category_id":19,"segmentation":[],"area":36967.56839999999,"bbox":[266.25,231.79,142.03,260.28],"iscrowd":0,"attributes":{"occluded":false,"keyframe":false},"keypoints":[330.83,242.58,1,338.23,232.67,1,318.01,231.79,1,342.76,239.53,1,311.7,243.58,1,367.46,269.41,2,286.83,277.85,2,392.15,310.76,2,266.25,324.44,2,408.28,315.6,2,280.28,329.03,1,375.4,380.5,1,323.9,389.48,2,390.96,438.83,1,334.33,436.89,2,406.02,487.41,1,346.28,492.07,1],"num_keypoints":17},{"id":43,"image_id":43,"category_id":19,"segmentation":[],"area":38629.28,"bbox":[262.42,234.88,152.0,254.14],"iscrowd":0,"attributes":{"occluded":false,"keyframe":false},"keypoints":[326.99,245.67,1,334.39,235.75,1,314.18,234.88,1,338.92,242.62,1,307.86,246.67,1,359.79,266.36,2,288.37,277.87,2,392.92,305.4,2,262.42,327.53,2,414.42,315.62,1,276.44,332.12,1,372.33,385.89,2,330.04,390.27,2,397.1,438.08,1,336.63,433.84,2,411.39,485.13,1,350.89,489.02,1],"num_keypoints":17},{"id":44,"image_id":44,"category_id":19,"segmentation":[],"area":38122.0502,"bbox":[260.5,231.05,150.46,253.37],"iscrowd":0,"attributes":{"occluded":false,"keyframe":false},"keypoints":[318.93,241.83,1,326.33,231.92,1,306.12,231.05,1,330.86,238.78,1,299.8,242.84,1,352.5,264.83,2,283.38,279.41,2,390.23,301.57,2,260.5,321.39,2,410.96,301.04,1,274.52,332.12,1,367.35,379.75,2,328.89,392.57,2,395.18,429.64,1,338.55,440.75,2,403.34,481.29,1,353.57,484.42,1],"num_keypoints":17},{"id":45,"image_id":45,"category_id":19,"segmentation":[],"area":37007.449499999995,"bbox":[251.29,232.97,152.05,243.39],"iscrowd":0,"attributes":{"occluded":false,"keyframe":false},"keypoints":[309.72,243.75,1,317.13,233.84,1,296.91,232.97,1,321.65,240.7,1,290.6,244.75,1,343.29,266.75,2,274.17,281.33,2,384.09,303.49,2,251.29,323.31,2,390.24,291.45,1,265.31,334.04,1,365.81,380.13,2,329.65,394.49,2,389.04,423.12,2,338.55,440.37,2,403.34,475.53,1,356.64,476.36,1],"num_keypoints":17},{"id":46,"image_id":46,"category_id":19,"segmentation":[],"area":37007.449499999995,"bbox":[251.29,232.97,152.05,243.39],"iscrowd":0,"attributes":{"occluded":false,"keyframe":false},"keypoints":[309.72,243.75,1,317.13,233.84,1,296.91,232.97,1,321.65,240.7,1,290.6,244.75,1,343.29,266.75,2,274.17,281.33,2,384.09,303.49,2,251.29,323.31,2,390.24,291.45,1,265.31,334.04,1,365.81,380.13,1,329.65,394.49,2,389.04,423.12,2,338.55,440.37,2,403.34,475.53,1,356.64,476.36,1],"num_keypoints":17},{"id":47,"image_id":47,"category_id":19,"segmentation":[],"area":37006.53599999999,"bbox":[254.34,231.81,152.04,243.4],"iscrowd":0,"attributes":{"occluded":false,"keyframe":false},"keypoints":[312.77,242.6,1,320.17,232.69,1,299.96,231.81,1,324.7,239.55,1,293.64,243.6,1,346.33,265.6,1,277.22,280.18,1,387.9,316.92,2,254.34,322.15,2,393.29,290.29,1,269.13,326.75,1,368.86,378.98,2,332.7,393.34,2,392.09,421.97,2,341.6,439.22,2,406.38,474.38,1,356.62,475.21,2],"num_keypoints":17},{"id":48,"image_id":48,"category_id":19,"segmentation":[],"area":38631.47640000001,"bbox":[256.64,234.88,159.72,241.87],"iscrowd":0,"attributes":{"occluded":false,"keyframe":false},"keypoints":[311.23,245.67,1,318.64,235.75,1,298.42,234.88,1,323.17,242.62,1,292.11,246.67,1,340.19,281.71,1,275.68,283.24,1,377.93,319.98,2,256.64,315.25,2,369.5,261.9,1,272.96,316.0,1,367.32,382.05,2,321.96,388.73,2,390.56,423.5,2,340.06,442.29,2,416.36,472.08,1,352.01,476.75,2],"num_keypoints":17},{"id":49,"image_id":49,"category_id":19,"segmentation":[],"area":39364.59119999999,"bbox":[252.8,237.19,159.72,246.46],"iscrowd":0,"attributes":{"occluded":false,"keyframe":false},"keypoints":[307.4,247.97,1,314.8,238.06,1,294.58,237.19,1,319.33,244.92,1,288.27,248.98,1,332.52,287.85,1,271.84,285.55,1,367.95,319.22,2,252.8,317.55,2,381.78,267.27,1,269.13,318.31,1,363.49,384.35,2,318.12,391.03,2,386.72,425.8,2,332.39,447.66,2,412.52,474.38,1,336.67,483.65,2],"num_keypoints":17},{"id":50,"image_id":50,"category_id":19,"segmentation":[],"area":39113.08959999999,"bbox":[250.5,247.93,164.32,238.03],"iscrowd":0,"attributes":{"occluded":false,"keyframe":false},"keypoints":[305.1,255.64,1,312.5,249.57,1,292.28,247.93,1,317.03,260.27,1,286.74,255.88,1,327.15,295.53,1,266.47,293.22,1,365.65,322.29,2,250.5,320.62,1,379.48,270.34,1,266.82,321.38,1,361.18,387.42,2,315.82,394.1,2,388.25,428.87,2,323.94,441.52,2,414.82,473.62,1,331.29,485.96,2],"num_keypoints":17},{"id":51,"image_id":51,"category_id":19,"segmentation":[],"area":40857.17949999999,"bbox":[240.52,258.29,177.37,230.35],"iscrowd":0,"attributes":{"occluded":false,"keyframe":false},"keypoints":[284.38,269.07,1,293.31,258.39,1,273.1,258.29,1,300.14,270.63,1,266.78,273.91,1,317.17,305.88,1,251.89,307.42,1,364.11,325.74,2,240.52,330.98,1,371.8,280.7,1,256.85,331.74,1,346.6,393.18,2,305.84,404.46,2,392.86,437.7,2,321.64,449.58,2,417.89,482.44,1,335.9,488.64,2],"num_keypoints":17},{"id":52,"image_id":52,"category_id":19,"segmentation":[],"area":40857.17949999999,"bbox":[240.52,258.29,177.37,230.35],"iscrowd":0,"attributes":{"occluded":false,"keyframe":false},"keypoints":[284.38,269.07,1,293.31,258.39,1,273.1,258.29,1,300.14,270.63,1,266.78,273.91,1,317.17,305.88,1,251.89,307.42,1,364.11,325.74,2,240.52,330.98,1,371.8,280.7,1,256.85,331.74,1,346.6,393.18,2,305.84,404.46,2,392.86,437.7,2,321.64,449.58,2,417.89,482.44,1,335.9,488.64,2],"num_keypoints":17},{"id":53,"image_id":78,"category_id":1,"segmentation":[],"area":37737.273600000015,"bbox":[31.29,496.21,231.12,163.28],"iscrowd":0,"attributes":{"occluded":false,"keyframe":false},"keypoints":[45.44,610.73,1,38.56,595.55,1,31.29,615.16,1,51.31,594.11,1,42.06,621.81,1,70.61,572.14,2,79.06,651.11,1,113.21,542.96,2,117.05,659.49,1,131.67,575.85,1,110.42,617.86,1,180.6,559.5,2,189.33,627.3,2,210.04,527.7,1,221.25,571.67,1,258.53,496.21,1,262.41,526.64,1],"num_keypoints":17},{"id":54,"image_id":79,"category_id":1,"segmentation":[],"area":41032.80899999999,"bbox":[25.25,486.74,241.1,170.19],"iscrowd":0,"attributes":{"occluded":false,"keyframe":false},"keypoints":[39.41,624.29,1,32.53,609.1,1,25.25,628.71,1,45.28,607.66,1,36.03,635.36,1,64.58,585.7,2,89.91,656.22,1,107.18,560.35,2,118.69,656.93,1,125.63,589.4,1,113.6,630.64,1,169.2,565.38,2,187.9,620.9,2,204.78,523.6,1,220.59,562.2,1,254.8,486.74,1,266.35,537.12,1],"num_keypoints":17},{"id":55,"image_id":80,"category_id":1,"segmentation":[],"area":43383.13289999999,"bbox":[19.5,487.86,254.91,170.19],"iscrowd":0,"attributes":{"occluded":false,"keyframe":false},"keypoints":[33.66,625.41,1,26.77,610.22,1,19.5,629.83,1,39.52,608.78,1,30.27,636.49,1,58.82,586.82,2,91.83,654.27,1,101.42,561.47,2,112.93,658.05,1,119.88,590.52,1,133.93,631.0,1,163.44,566.5,2,182.15,622.02,2,199.02,524.72,1,214.83,563.32,1,249.04,487.86,1,274.41,540.54,1],"num_keypoints":17},{"id":56,"image_id":81,"category_id":1,"segmentation":[],"area":42534.78919999999,"bbox":[24.47,488.63,249.94,170.18],"iscrowd":0,"attributes":{"occluded":false,"keyframe":false},"keypoints":[36.72,626.94,1,24.47,617.89,1,26.4,631.37,1,37.22,614.92,1,36.41,638.79,1,58.82,587.58,2,88.76,653.5,1,101.42,562.23,2,112.93,658.81,1,119.88,591.29,1,133.93,631.76,1,163.44,567.27,2,182.14,622.79,2,199.02,525.49,1,214.83,564.09,1,249.04,488.63,1,274.41,541.31,1],"num_keypoints":17},{"id":57,"image_id":82,"category_id":1,"segmentation":[],"area":42534.78919999999,"bbox":[24.47,488.63,249.94,170.18],"iscrowd":0,"attributes":{"occluded":false,"keyframe":false},"keypoints":[36.72,626.94,1,24.47,617.89,1,26.4,631.37,1,37.22,614.92,1,36.41,638.79,1,58.82,587.58,2,87.22,651.97,1,101.42,562.23,2,112.93,658.81,1,119.88,591.29,1,133.93,631.76,1,163.44,567.27,2,182.14,622.79,2,199.02,525.49,1,214.83,564.09,1,249.04,488.63,1,274.41,541.31,1],"num_keypoints":17},{"id":58,"image_id":83,"category_id":1,"segmentation":[],"area":42537.288599999985,"bbox":[19.68,487.86,249.94,170.19],"iscrowd":0,"attributes":{"occluded":false,"keyframe":false},"keypoints":[31.94,626.17,1,19.68,617.13,1,21.62,630.6,1,32.43,614.16,1,31.62,638.02,1,54.03,586.82,2,86.27,652.74,1,96.63,561.47,2,108.14,658.05,1,115.09,590.52,1,129.15,631.0,1,158.66,566.5,2,177.36,622.02,2,194.23,524.72,1,210.05,563.32,1,244.26,487.86,1,269.62,540.54,1],"num_keypoints":17},{"id":59,"image_id":84,"category_id":1,"segmentation":[],"area":43655.15,"bbox":[18.92,480.19,253.0,172.55],"iscrowd":0,"attributes":{"occluded":false,"keyframe":false},"keypoints":[31.17,618.5,1,18.92,609.45,1,20.85,622.92,1,31.66,606.48,1,30.85,630.35,1,55.57,589.12,2,83.97,652.74,1,94.33,564.53,2,107.38,650.37,1,114.32,582.85,1,128.38,623.32,1,157.89,558.83,2,176.59,614.35,2,193.47,517.05,1,212.35,562.56,1,243.49,480.19,1,271.92,542.08,1],"num_keypoints":17},{"id":60,"image_id":85,"category_id":1,"segmentation":[],"area":43109.651199999986,"bbox":[18.15,484.41,249.94,172.48],"iscrowd":0,"attributes":{"occluded":false,"keyframe":false},"keypoints":[30.4,625.02,1,18.15,615.98,1,20.08,629.45,1,30.9,613.0,1,30.09,636.87,1,52.5,585.66,2,80.13,654.66,1,85.12,566.45,2,106.61,656.89,1,108.18,587.83,1,127.61,629.84,1,157.12,565.35,2,171.22,617.8,2,189.63,515.13,1,203.14,565.24,1,238.88,484.41,1,268.09,546.3,1],"num_keypoints":17},{"id":61,"image_id":86,"category_id":1,"segmentation":[],"area":42348.57360000001,"bbox":[16.61,487.09,252.24,167.89],"iscrowd":0,"attributes":{"occluded":false,"keyframe":false},"keypoints":[28.87,623.1,1,16.61,614.06,1,18.55,627.53,1,29.36,611.09,1,28.55,634.95,1,50.19,589.89,2,78.6,654.27,1,87.42,567.6,2,105.07,654.98,1,99.74,589.75,1,126.07,627.93,1,155.58,563.43,2,175.82,610.51,2,190.39,514.75,1,201.6,563.32,1,238.88,487.09,1,268.85,549.75,1],"num_keypoints":17},{"id":62,"image_id":87,"category_id":1,"segmentation":[],"area":42549.78560000002,"bbox":[21.6,486.33,249.94,170.24],"iscrowd":0,"attributes":{"occluded":false,"keyframe":false},"keypoints":[31.55,622.33,1,21.6,622.5,1,22.77,629.83,1,32.81,614.16,1,31.24,634.18,1,52.88,589.12,2,82.82,656.57,1,90.11,566.84,2,107.76,654.21,1,102.43,588.98,1,128.76,627.16,1,158.27,562.66,2,174.67,614.35,2,193.08,513.98,1,204.29,562.56,1,241.57,486.33,1,271.54,548.99,1],"num_keypoints":17},{"id":63,"image_id":88,"category_id":1,"segmentation":[],"area":42359.83119999999,"bbox":[21.6,486.33,249.94,169.48],"iscrowd":0,"attributes":{"occluded":false,"keyframe":false},"keypoints":[31.55,622.33,1,21.6,622.5,1,22.77,629.83,1,32.81,614.16,1,31.24,634.18,1,52.88,589.12,2,81.28,655.81,1,90.11,566.84,2,107.76,654.21,1,102.43,588.98,1,128.76,627.16,1,158.27,562.66,2,174.67,614.35,2,193.08,513.98,1,204.29,562.56,1,241.57,486.33,1,271.54,548.99,1],"num_keypoints":17},{"id":64,"image_id":89,"category_id":1,"segmentation":[],"area":41400.0616,"bbox":[21.6,488.63,249.94,165.64],"iscrowd":0,"attributes":{"occluded":false,"keyframe":false},"keypoints":[31.55,622.33,1,21.6,622.5,1,22.77,629.83,1,32.81,614.16,1,31.24,634.18,1,52.88,589.12,2,81.28,654.27,1,90.11,566.84,2,107.76,654.21,1,102.43,588.98,1,128.76,627.16,1,158.27,562.66,2,174.67,614.35,2,197.68,518.58,1,204.29,562.56,1,243.1,488.63,1,271.54,548.99,1],"num_keypoints":17},{"id":65,"image_id":90,"category_id":1,"segmentation":[],"area":39850.43360000002,"bbox":[21.6,494.77,249.94,159.44],"iscrowd":0,"attributes":{"occluded":false,"keyframe":false},"keypoints":[31.55,622.33,1,21.6,622.5,1,22.77,629.83,1,32.81,614.16,1,31.24,634.18,1,52.88,589.12,2,77.45,647.37,1,90.11,566.84,2,107.76,654.21,1,102.43,588.98,1,128.76,627.16,1,158.27,562.66,2,174.67,614.35,2,196.92,524.72,1,204.29,562.56,1,244.64,494.77,1,271.54,542.85,1],"num_keypoints":17},{"id":66,"image_id":91,"category_id":1,"segmentation":[],"area":36206.30840000001,"bbox":[21.6,509.35,249.94,144.86],"iscrowd":0,"attributes":{"occluded":false,"keyframe":false},"keypoints":[31.55,622.33,1,21.6,622.5,1,22.77,629.83,1,32.81,614.16,1,31.24,634.18,1,52.88,589.12,2,74.38,649.67,1,90.11,566.84,2,107.76,654.21,1,102.43,588.98,1,128.76,627.16,1,158.27,562.66,2,174.67,614.35,2,194.62,530.86,1,204.29,562.56,1,250.78,509.35,1,271.54,542.85,1],"num_keypoints":17},{"id":67,"image_id":92,"category_id":1,"segmentation":[],"area":33418.6804,"bbox":[21.6,520.09,249.17,134.12],"iscrowd":0,"attributes":{"occluded":false,"keyframe":false},"keypoints":[31.55,622.33,1,21.6,622.5,1,22.77,629.83,1,32.81,614.16,1,31.24,634.18,1,52.88,589.12,2,75.91,649.67,1,90.11,566.84,2,107.76,654.21,1,102.43,588.98,1,128.76,627.16,1,158.27,562.66,2,178.51,618.18,2,198.45,529.33,1,204.29,562.56,1,261.52,520.09,1,270.77,540.54,1],"num_keypoints":17},{"id":68,"image_id":93,"category_id":1,"segmentation":[],"area":33418.6804,"bbox":[21.6,520.09,249.17,134.12],"iscrowd":0,"attributes":{"occluded":false,"keyframe":false},"keypoints":[31.55,622.33,1,21.6,622.5,1,22.77,629.83,1,32.81,614.16,1,31.24,634.18,1,52.88,589.12,2,75.14,651.2,1,90.11,566.84,2,107.76,654.21,1,102.43,588.98,1,128.76,627.16,1,165.18,563.43,2,178.51,618.18,2,200.75,536.24,1,204.29,562.56,1,261.52,520.09,1,270.77,540.54,1],"num_keypoints":17},{"id":69,"image_id":94,"category_id":1,"segmentation":[],"area":33418.6804,"bbox":[21.6,520.09,249.17,134.12],"iscrowd":0,"attributes":{"occluded":false,"keyframe":false},"keypoints":[31.55,622.33,1,21.6,622.5,1,22.77,629.83,1,32.81,614.16,1,31.24,634.18,1,52.88,589.12,2,77.45,650.44,1,90.11,566.84,2,107.76,654.21,1,102.43,588.98,1,128.76,627.16,1,165.18,563.43,2,178.51,618.18,2,200.75,536.24,1,204.29,562.56,1,261.52,520.09,1,270.77,540.54,1],"num_keypoints":17},{"id":70,"image_id":95,"category_id":1,"segmentation":[],"area":33418.6804,"bbox":[21.6,520.09,249.17,134.12],"iscrowd":0,"attributes":{"occluded":false,"keyframe":false},"keypoints":[31.55,622.33,1,21.6,622.5,1,22.77,629.83,1,32.81,614.16,1,31.24,634.18,1,55.18,586.05,2,75.14,651.97,1,90.11,566.84,2,107.76,654.21,1,102.43,588.98,1,128.76,627.16,1,165.18,563.43,2,178.51,618.18,2,200.75,536.24,1,204.29,562.56,1,261.52,520.09,1,270.77,540.54,1],"num_keypoints":17},{"id":71,"image_id":96,"category_id":1,"segmentation":[],"area":33418.6804,"bbox":[18.53,521.27,249.17,134.12],"iscrowd":0,"attributes":{"occluded":false,"keyframe":false},"keypoints":[28.48,623.52,1,18.53,623.68,1,19.7,631.01,1,29.75,615.34,1,28.17,635.36,1,52.11,587.23,2,72.07,653.15,1,87.04,568.02,2,104.69,655.39,1,99.36,590.17,1,125.69,628.34,1,166.71,569.98,2,183.11,623.97,2,197.69,537.42,1,201.22,563.74,1,258.45,521.27,1,267.7,541.73,1],"num_keypoints":17},{"id":72,"image_id":97,"category_id":1,"segmentation":[],"area":33418.6804,"bbox":[18.53,521.27,249.17,134.12],"iscrowd":0,"attributes":{"occluded":false,"keyframe":false},"keypoints":[28.48,623.52,1,18.53,623.68,1,19.7,631.01,1,29.75,615.34,1,28.17,635.36,1,52.11,587.23,2,72.07,653.15,1,87.04,568.02,2,104.69,655.39,1,99.36,590.17,1,125.69,628.34,1,173.62,568.45,2,183.11,623.97,2,197.69,537.42,1,201.22,563.74,1,258.45,521.27,1,267.7,541.73,1],"num_keypoints":17}]}